Workbook

Sheet Control Panel
A1: GMGL ACCOUNTS – REPORT CONTROLS
A2: Report Period | B2: Start Date | C2: End Date
B3: 46113 | C3: 46173
A5: NOTE: ALL SALES ARE CASH ONLY. No credit sales permitted.
A7: Opening Bank Balance (GHS) | B7: 1000

Sheet Setup
A1: SETUP – REFERENCE DATA
A2: All Shops | C2: All Products | E2: Trading Shops | G2: Egg Products | J2: Farm Cost Items
A3: Akatsi Feed | C3: LM | E3: Akatsi Feed | G3: Extra Large | J3: Maize
A4: Abor Feed | C4: GM | E4: Abor Feed | G4: Large | J4: Soya
A5: Mobile Shop | C5: CM | E5: Mobile Shop | G5: Medium | J5: Concentrate
A6: Egg Shop | C6: BS | G6: Small | J6: GMG
C7: Hend 5% | G7: Pullet 1 | J7: Shell
C8: GMG | G8: Pullet 2 | J8: Salary
C9: Crates | G9: Broken | J9: Transport
C10: Extra Large | J10: Medication
C11: Large | J11: Utilities
C12: Medium | J12: Other
C13: Small
C14: Pullet 1
C15: Pullet 2
C16: Broken

Sheet Chart of Accounts
A1: CHART OF ACCOUNTS
A2: Code | B2: Account Name | C2: Type | D2: Notes
A3: 1000 | B3: Cash at Bank | C3: Asset | D3: Auto from Sales
A4: 1010 | B4: Trading Stock | C4: Asset | D4: From Stock Summary
A5: 1020 | B5: Egg Stock | C5: Asset | D5: From Stock Summary
A6: 1030 | B6: Feed Ingredients | C6: Asset | D6: From Feed Inventory
A7: 2000 | B7: Accounts Payable | C7: Liability | D7: Supplier invoices
A8: 2010 | B8: Accrued Expenses | C8: Liability | D8: Expenses not yet paid
A9: 3000 | B9: Owner Equity | C9: Equity | D9: Opening capital
A10: 3010 | B10: Retained Earnings | C10: Equity | D10: Accumulated net profit
A11: 4000 | B11: Trading Shop Sales | C11: Income | D11: Cash only
A12: 4010 | B12: Egg Shop Sales | C12: Income | D12: Cash only
A13: 5000 | B13: Cost of Goods Sold | C13: Cost of Sales | D13: Auto from Sales Log
... A20: 6050 | B20: Other Expenses | C20: Expense | D20: Miscellaneous

Sheet Purchases
A1: PURCHASES LOG
A2: Date | B2: Supplier | C2: Shop | D2: Product | E2: Qty Purchased | F2: Unit Cost (GHS) | G2: Total Cost (GHS) | H2: Key
A3: 46113 | B3: Sankofa | C3: Akatsi Feed | D3: LM | E3: 64 | F3: 352 | G3: =IF(OR(E3="",F3=""),"",E3*F3) -> 22528 | H3: =IF(OR(C3="",D3=""),"",C3&"|"&D3) -> Akatsi Feed|LM
A4: 46113 | B4: Sankofa | C4: Akatsi Feed | D4: GM | E4: 23 | F4: 340 | G4: =IF(OR(E4="",F4=""),"",E4*F4) -> 7820 | H4: =IF(OR(C4="",D4=""),"",C4&"|"&D4) -> Akatsi Feed|GM
A5: 46113 | B5: Sankofa | C5: Akatsi Feed | D5: CM | E5: 8 | F5: 357 | G5: =IF(OR(E5="",F5=""),"",E5*F5) -> 2856 | H5: =IF(OR(C5="",D5=""),"",C5&"|"&D5) -> Akatsi Feed|CM
A6: 46113 | B6: Sankofa | C6: Akatsi Feed | D6: BS | E6: 0 | F6: 395 | G6: =IF(OR(E6="",F6=""),"",E6*F6) -> 0 | H6: =IF(OR(C6="",D6=""),"",C6&"|"&D6) -> Akatsi Feed|BS
A7: 46113 | B7: Sankofa | C7: Akatsi Feed | D7: Hend 5% | E7: 0 | F7: 730 | G7: =IF(OR(E7="",F7=""),"",E7*F7) -> 0 | H7: =IF(OR(C7="",D7=""),"",C7&"|"&D7) -> Akatsi Feed|Hend 5%
A8: 46113 | B8: Sankofa | C8: Akatsi Feed | D8: GMG | E8: 0 | F8: 80 | G8: =IF(OR(E8="",F8=""),"",E8*F8) -> 0 | H8: =IF(OR(C8="",D8=""),"",C8&"|"&D8) -> Akatsi Feed|GMG
A9: 46113 | B9: Sankofa | C9: Akatsi Feed | D9: Crates | E9: 44 | F9: 80 | G9: =IF(OR(E9="",F9=""),"",E9*F9) -> 3520 | H9: =IF(OR(C9="",D9=""),"",C9&"|"&D9) -> Akatsi Feed|Crates
A10: 46113 | B10: Sankofa | C10: Abor Feed | D10: LM | E10: 21 | F10: 352 | G10: =IF(OR(E10="",F10=""),"",E10*F10) -> 7392 | H10: =IF(OR(C10="",D10=""),"",C10&"|"&D10) -> Abor Feed|LM
A11: 46113 | B11: Sankofa | C11: Abor Feed | D11: GM | E11: 3 | F11: 340 | G11: =IF(OR(E11="",F11=""),"",E11*F11) -> 1020 | H11: =IF(OR(C11="",D11=""),"",C11&"|"&D11) -> Abor Feed|GM
A12: 46113 | B12: Sankofa | C12: Abor Feed | D12: CM | E12: 0 | F12: 357 | G12: =IF(OR(E12="",F12=""),"",E12*F12) -> 0 | H12: =IF(OR(C12="",D12=""),"",C12&"|"&D12) -> Abor Feed|CM
A13: 46113 | B13: Sankofa | C13: Abor Feed | D13: BS | E13: 0 | F13: 395 | G13: =IF(OR(E13="",F13=""),"",E13*F13) -> 0 | H13: =IF(OR(C13="",D13=""),"",C13&"|"&D13) -> Abor Feed|BS
A14: 46113 | B14: Sankofa | C14: Abor Feed | D14: GMG | E14: 0 | F14: 80 | G14: =IF(OR(E14="",F14=""),"",E14*F14) -> 0 | H14: =IF(OR(C14="",D14=""),"",C14&"|"&D14) -> Abor Feed|GMG
... A22: 46120 | B22: Sankofa | C22: Mobile Shop | D22: Hend 5% | E22: 0 | F22: 730 | G22: =IF(OR(E22="",F22=""),"",E22*F22) -> 0 | H22: =IF(OR(C22="",D22=""),"",C22&"|"&D22) -> Mobile Shop|Hend 5%
A23: 46113 | B23: Sankofa | C23: Mobile Shop | E23: 0 | F23: 80 | G23: =IF(OR(E23="",F23=""),"",E23*F23) -> 0 | H23: =IF(OR(C23="",D23=""),"",C23&"|"&D23)
A24: 46113 | B24: GMGL | C24: Egg Shop | E24: 0 | F24: 69.5 | G24: =IF(OR(E24="",F24=""),"",E24*F24) -> 0 | H24: =IF(OR(C24="",D24=""),"",C24&"|"&D24)
A25: 46113 | B25: GMGL | C25: Egg Shop | E25: 0 | F25: 59.5 | G25: =IF(OR(E25="",F25=""),"",E25*F25) -> 0 | H25: =IF(OR(C25="",D25=""),"",C25&"|"&D25)
A26: 46113 | B26: GMGL | C26: Egg Shop | E26: 13 | F26: 57.5 | G26: =IF(OR(E26="",F26=""),"",E26*F26) -> 747.5 | H26: =IF(OR(C26="",D26=""),"",C26&"|"&D26)
A27: 46113 | B27: GMGL | C27: Egg Shop | E27: 17 | F27: 54.5 | G27: =IF(OR(E27="",F27=""),"",E27*F27) -> 926.5 | H27: =IF(OR(C27="",D27=""),"",C27&"|"&D27)
A28: 46113 | B28: GMGL | C28: Egg Shop | E28: 14 | F28: 39.5 | G28: =IF(OR(E28="",F28=""),"",E28*F28) -> 553 | H28: =IF(OR(C28="",D28=""),"",C28&"|"&D28)
A29: 46113 | B29: GMGL | C29: Egg Shop | E29: 0 | F29: 34.5 | G29: =IF(OR(E29="",F29=""),"",E29*F29) -> 0 | H29: =IF(OR(C29="",D29=""),"",C29&"|"&D29)
A30: 46113 | B30: GMGL | C30: Egg Shop | E30: 4 | F30: 29.5 | G30: =IF(OR(E30="",F30=""),"",E30*F30) -> 118 | H30: =IF(OR(C30="",D30=""),"",C30&"|"&D30)
A31: 46129 | B31: Sankofa | C31: Akatsi Feed | D31: LM | E31: 0 | F31: 352 | G31: =IF(OR(E31="",F31=""),"",E31*F31) -> 0 | H31: =IF(OR(C31="",D31=""),"",C31&"|"&D31) -> Akatsi Feed|LM
A32: 46129 | B32: Sankofa | C32: Akatsi Feed | D32: GM | E32: 0 | F32: 340 | G32: =IF(OR(E32="",F32=""),"",E32*F32) -> 0 | H32: =IF(OR(C32="",D32=""),"",C32&"|"&D32) -> Akatsi Feed|GM
A33: 46129 | B33: Sankofa | C33: Abor Feed | D33: LM | E33: 13 | F33: 352 | G33: =IF(OR(E33="",F33=""),"",E33*F33) -> 4576 | H33: =IF(OR(C33="",D33=""),"",C33&"|"&D33) -> Abor Feed|LM
A34: 46129 | B34: Sankofa | C34: Abor Feed | D34: GM | E34: 3 | F34: 340 | G34: =IF(OR(E34="",F34=""),"",E34*F34) -> 1020 | H34: =IF(OR(C34="",D34=""),"",C34&"|"&D34) -> Abor Feed|GM
A35: 46129 | B35: Sankofa | C35: Mobile Shop | D35: LM | E35: 50 | F35: 352 | G35: =IF(OR(E35="",F35=""),"",E35*F35) -> 17600 | H35: =IF(OR(C35="",D35=""),"",C35&"|"&D35) -> Mobile Shop|LM
A36: 46129 | B36: Sankofa | C36: Mobile Shop | D36: Hend 5% | E36: 4 | F36: 730 | G36: =IF(OR(E36="",F36=""),"",E36*F36) -> 2920 | H36: =IF(OR(C36="",D36=""),"",C36&"|"&D36) -> Mobile Shop|Hend 5%
A37: 46135 | B37: Sankofa | C37: Akatsi Feed | D37: Crates | E37: 20 | F37: 80 | G37: =IF(OR(E37="",F37=""),"",E37*F37) -> 1600 | H37: =IF(OR(C37="",D37=""),"",C37&"|"&D37) -> Akatsi Feed|Crates
A38: 46135 | B38: Sankofa | C38: Akatsi Feed | D38: LM | E38: 90 | F38: 352 | G38: =IF(OR(E38="",F38=""),"",E38*F38) -> 31680 | H38: =IF(OR(C38="",D38=""),"",C38&"|"&D38) -> Akatsi Feed|LM
A39: 46135 | B39: Sankofa | C39: Akatsi Feed | D39: GM | E39: 30 | F39: 340 | G39: =IF(OR(E39="",F39=""),"",E39*F39) -> 10200 | H39: =IF(OR(C39="",D39=""),"",C39&"|"&D39) -> Akatsi Feed|GM
A40: 46135 | B40: Sankofa | C40: Abor Feed | D40: LM | E40: 56 | F40: 352 | G40: =IF(OR(E40="",F40=""),"",E40*F40) -> 19712 | H40: =IF(OR(C40="",D40=""),"",C40&"|"&D40) -> Abor Feed|LM
A41: 46135 | B41: Sankofa | C41: Abor Feed | D41: GM | E41: 10 | F41: 340 | G41: =IF(OR(E41="",F41=""),"",E41*F41) -> 3400 | H41: =IF(OR(C41="",D41=""),"",C41&"|"&D41) -> Abor Feed|GM
A42: 46135 | B42: Sankofa | C42: Mobile Shop | D42: LM | E42: 60 | F42: 352 | G42: =IF(OR(E42="",F42=""),"",E42*F42) -> 21120 | H42: =IF(OR(C42="",D42=""),"",C42&"|"&D42) -> Mobile Shop|LM
... A53: 46142 | B53: Sankofa | C53: Mobile Shop | D53: Hend 5% | E53: 10 | F53: 730 | G53: =IF(OR(E53="",F53=""),"",E53*F53) -> 7300 | H53: =IF(OR(C53="",D53=""),"",C53&"|"&D53) -> Mobile Shop|Hend 5%
A54: 46142 | G54: =IF(OR(E54="",F54=""),"",E54*F54) | H54: =IF(OR(C54="",D54=""),"",C54&"|"&D54)
A55: 46142 | G55: =IF(OR(E55="",F55=""),"",E55*F55) | H55: =IF(OR(C55="",D55=""),"",C55&"|"&D55)
A56: 46142 | G56: =IF(OR(E56="",F56=""),"",E56*F56) | H56: =IF(OR(C56="",D56=""),"",C56&"|"&D56)
G57: =IF(OR(E57="",F57=""),"",E57*F57) | H57: =IF(OR(C57="",D57=""),"",C57&"|"&D57)
G58: =IF(OR(E58="",F58=""),"",E58*F58) | H58: =IF(OR(C58="",D58=""),"",C58&"|"&D58)
G59: =IF(OR(E59="",F59=""),"",E59*F59) | H59: =IF(OR(C59="",D59=""),"",C59&"|"&D59)
G60: =IF(OR(E60="",F60=""),"",E60*F60) | H60: =IF(OR(C60="",D60=""),"",C60&"|"&D60)
G61: =IF(OR(E61="",F61=""),"",E61*F61) | H61: =IF(OR(C61="",D61=""),"",C61&"|"&D61)
G62: =IF(OR(E62="",F62=""),"",E62*F62) | H62: =IF(OR(C62="",D62=""),"",C62&"|"&D62)
G63: =IF(OR(E63="",F63=""),"",E63*F63) | H63: =IF(OR(C63="",D63=""),"",C63&"|"&D63)
G64: =IF(OR(E64="",F64=""),"",E64*F64) | H64: =IF(OR(C64="",D64=""),"",C64&"|"&D64)
G65: =IF(OR(E65="",F65=""),"",E65*F65) | H65: =IF(OR(C65="",D65=""),"",C65&"|"&D65)
G66: =IF(OR(E66="",F66=""),"",E66*F66) | H66: =IF(OR(C66="",D66=""),"",C66&"|"&D66)
G67: =IF(OR(E67="",F67=""),"",E67*F67) | H67: =IF(OR(C67="",D67=""),"",C67&"|"&D67)
G68: =IF(OR(E68="",F68=""),"",E68*F68) | H68: =IF(OR(C68="",D68=""),"",C68&"|"&D68)
... G1049: =IF(OR(E1049="",F1049=""),"",E1049*F1049) | H1049: =IF(OR(C1049="",D1049=""),"",C1049&"|"&D1049)

Sheet Sales Log
A1: CASH SALES ONLY – No credit sales. Every sale settled immediately in cash.
A2: Date | B2: Shop | C2: Product | D2: Qty Sold | E2: Selling Price (GHS) | F2: Cost Price (Auto) | G2: Total Sales (GHS) | H2: Total Cost (GHS) | I2: Gross Profit (GHS) | J2: Key | K2: Payment
A3: 46114 | B3: Akatsi Feed | C3: LM | D3: 1 | E3: 365 | F3: =IF(B3="Egg Shop","",IF(J3="","",IFERROR(LOOKUP(2,1/(Purchases!$H$3:$H$2002=J3),Purchases!$F$3:$F$2002),""))) -> 352 | G3: =IF(OR(D3="",E3=""),"",D3*E3) -> 365 | H3: =IF(OR(D3="",F3=""),"",D3*F3) -> 352 | I3: =IF(OR(G3="",H3=""),"",G3-H3) -> 13 | J3: =IF(OR(B3="",C3=""),"",B3&"|"&C3) -> Akatsi Feed|LM | K3: Cash
A4: 46115 | B4: Akatsi Feed | C4: LM | D4: 7 | E4: 365 | F4: =IF(B4="Egg Shop","",IF(J4="","",IFERROR(LOOKUP(2,1/(Purchases!$H$3:$H$2002=J4),Purchases!$F$3:$F$2002),""))) -> 352 | G4: =IF(OR(D4="",E4=""),"",D4*E4) -> 2555 | H4: =IF(OR(D4="",F4=""),"",D4*F4) -> 2464 | I4: =IF(OR(G4="",H4=""),"",G4-H4) -> 91 | J4: =IF(OR(B4="",C4=""),"",B4&"|"&C4) -> Akatsi Feed|LM | K4: Cash
A5: 46115 | B5: Akatsi Feed | C5: GM | D5: 2 | E5: 350 | F5: =IF(B5="Egg Shop","",IF(J5="","",IFERROR(LOOKUP(2,1/(Purchases!$H$3:$H$2002=J5),Purchases!$F$3:$F$2002),""))) -> 340 | G5: =IF(OR(D5="",E5=""),"",D5*E5) -> 700 | H5: =IF(OR(D5="",F5=""),"",D5*F5) -> 680 | I5: =IF(OR(G5="",H5=""),"",G5-H5) -> 20 | J5: =IF(OR(B5="",C5=""),"",B5&"|"&C5) -> Akatsi Feed|GM | K5: Cash
A6: 46115 | B6: Akatsi Feed | C6: Crates | D6: 6 | E6: 90 | F6: =IF(B6="Egg Shop","",IF(J6="","",IFERROR(LOOKUP(2,1/(Purchases!$H$3:$H$2002=J6),Purchases!$F$3:$F$2002),""))) -> 80 | G6: =IF(OR(D6="",E6=""),"",D6*E6) -> 540 | H6: =IF(OR(D6="",F6=""),"",D6*F6) -> 480 | I6: =IF(OR(G6="",H6=""),"",G6-H6) -> 60 | J6: =IF(OR(B6="",C6=""),"",B6&"|"&C6) -> Akatsi Feed|Crates | K6: Cash
A7: 46116 | B7: Akatsi Feed | C7: LM | D7: 7 | E7: 365 | F7: =IF(B7="Egg Shop","",IF(J7="","",IFERROR(LOOKUP(2,1/(Purchases!$H$3:$H$2002=J7),Purchases!$F$3:$F$2002),""))) -> 352 | G7: =IF(OR(D7="",E7=""),"",D7*E7) -> 2555 | H7: =IF(OR(D7="",F7=""),"",D7*F7) -> 2464 | I7: =IF(OR(G7="",H7=""),"",G7-H7) -> 91 | J7: =IF(OR(B7="",C7=""),"",B7&"|"&C7) -> Akatsi Feed|LM | K7: Cash
A8: 46116 | B8: Akatsi Feed | C8: GM | D8: 6 | E8: 350 | F8: =IF(B8="Egg Shop","",IF(J8="","",IFERROR(LOOKUP(2,1/(Purchases!$H$3:$H$2002=J8),Purchases!$F$3:$F$2002),""))) -> 340 | G8: =IF(OR(D8="",E8=""),"",D8*E8) -> 2100 | H8: =IF(OR(D8="",F8=""),"",D8*F8) -> 2040 | I8: =IF(OR(G8="",H8=""),"",G8-H8) -> 60 | J8: =IF(OR(B8="",C8=""),"",B8&"|"&C8) -> Akatsi Feed|GM | K8: Cash
A9: 46116 | B9: Akatsi Feed | C9: CM | D9: 1 | E9: 370 | F9: =IF(B9="Egg Shop","",IF(J9="","",IFERROR(LOOKUP(2,1/(Purchases!$H$3:$H$2002=J9),Purchases!$F$3:$F$2002),""))) -> 357 | G9: =IF(OR(D9="",E9=""),"",D9*E9) -> 370 | H9: =IF(OR(D9="",F9=""),"",D9*F9) -> 357 | I9: =IF(OR(G9="",H9=""),"",G9-H9) -> 13 | J9: =IF(OR(B9="",C9=""),"",B9&"|"&C9) -> Akatsi Feed|CM | K9: Cash
A10: 46116 | B10: Akatsi Feed | C10: Crates | D10: 2 | E10: 90 | F10: =IF(B10="Egg Shop","",IF(J10="","",IFERROR(LOOKUP(2,1/(Purchases!$H$3:$H$2002=J10),Purchases!$F$3:$F$2002),""))) -> 80 | G10: =IF(OR(D10="",E10=""),"",D10*E10) -> 180 | H10: =IF(OR(D10="",F10=""),"",D10*F10) -> 160 | I10: =IF(OR(G10="",H10=""),"",G10-H10) -> 20 | J10: =IF(OR(B10="",C10=""),"",B10&"|"&C10) -> Akatsi Feed|Crates | K10: Cash
A11: 46118 | B11: Akatsi Feed | C11: LM | D11: 30 | E11: 365 | F11: =IF(B11="Egg Shop","",IF(J11="","",IFERROR(LOOKUP(2,1/(Purchases!$H$3:$H$2002=J11),Purchases!$F$3:$F$2002),""))) -> 352 | G11: =IF(OR(D11="",E11=""),"",D11*E11) -> 10950 | H11: =IF(OR(D11="",F11=""),"",D11*F11) -> 10560 | I11: =IF(OR(G11="",H11=""),"",G11-H11) -> 390 | J11: =IF(OR(B11="",C11=""),"",B11&"|"&C11) -> Akatsi Feed|LM | K11: Cash
A12: 46118 | B12: Akatsi Feed | C12: GM | D12: 2 | E12: 350 | F12: =IF(B12="Egg Shop","",IF(J12="","",IFERROR(LOOKUP(2,1/(Purchases!$H$3:$H$2002=J12),Purchases!$F$3:$F$2002),""))) -> 340 | G12: =IF(OR(D12="",E12=""),"",D12*E12) -> 700 | H12: =IF(OR(D12="",F12=""),"",D12*F12) -> 680 | I12: =IF(OR(G12="",H12=""),"",G12-H12) -> 20 | J12: =IF(OR(B12="",C12=""),"",B12&"|"&C12) -> Akatsi Feed|GM | K12: Cash
A13: 46118 | B13: Akatsi Feed | C13: Crates | D13: 5 | E13: 90 | F13: =IF(B13="Egg Shop","",IF(J13="","",IFERROR(LOOKUP(2,1/(Purchases!$H$3:$H$2002=J13),Purchases!$F$3:$F$2002),""))) -> 80 | G13: =IF(OR(D13="",E13=""),"",D13*E13) -> 450 | H13: =IF(OR(D13="",F13=""),"",D13*F13) -> 400 | I13: =IF(OR(G13="",H13=""),"",G13-H13) -> 50 | J13: =IF(OR(B13="",C13=""),"",B13&"|"&C13) -> Akatsi Feed|Crates | K13: Cash
A14: 46113 | B14: Abor Feed | C14: LM | D14: 3 | E14: 365 | F14: =IF(B14="Egg Shop","",IF(J14="","",IFERROR(LOOKUP(2,1/(Purchases!$H$3:$H$2002=J14),Purchases!$F$3:$F$2002),""))) -> 352 | G14: =IF(OR(D14="",E14=""),"",D14*E14) -> 1095 | H14: =IF(OR(D14="",F14=""),"",D14*F14) -> 1056 | I14: =IF(OR(G14="",H14=""),"",G14-H14) -> 39 | J14: =IF(OR(B14="",C14=""),"",B14&"|"&C14) -> Abor Feed|LM | K14: Cash
... A40: 46122 | B40: Akatsi Feed | C40: Crates | D40: 0 | E40: 90 | F40: =IF(B40="Egg Shop","",IF(J40="","",IFERROR(LOOKUP(2,1/(Purchases!$H$3:$H$2002=J40),Purchases!$F$3:$F$2002),""))) -> 80 | G40: =IF(OR(D40="",E40=""),"",D40*E40) -> 0 | H40: =IF(OR(D40="",F40=""),"",D40*F40) -> 0 | I40: =IF(OR(G40="",H40=""),"",G40-H40) -> 0 | J40: =IF(OR(B40="",C40=""),"",B40&"|"&C40) -> Akatsi Feed|Crates | K40: Cash
A41: 46113 | B41: Egg Shop | C41: Large | D41: 0 | E41: 60 | F41: 60 | G41: =IF(OR(D41="",E41=""),"",D41*E41) -> 0 | H41: =IF(OR(D41="",F41=""),"",D41*F41) -> 0 | I41: =IF(OR(G41="",H41=""),"",G41-H41) -> 0 | J41: =IF(OR(B41="",C41=""),"",B41&"|"&C41) -> Egg Shop|Large | K41: Cash
A42: 46113 | B42: Egg Shop | C42: Medium | D42: 10 | E42: 58 | F42: 58 | G42: =IF(OR(D42="",E42=""),"",D42*E42) -> 580 | H42: =IF(OR(D42="",F42=""),"",D42*F42) -> 580 | I42: =IF(OR(G42="",H42=""),"",G42-H42) -> 0 | J42: =IF(OR(B42="",C42=""),"",B42&"|"&C42) -> Egg Shop|Medium | K42: Cash
A43: 46113 | B43: Egg Shop | C43: Small | D43: 0 | E43: 55 | F43: 55 | G43: =IF(OR(D43="",E43=""),"",D43*E43) -> 0 | H43: =IF(OR(D43="",F43=""),"",D43*F43) -> 0 | I43: =IF(OR(G43="",H43=""),"",G43-H43) -> 0 | J43: =IF(OR(B43="",C43=""),"",B43&"|"&C43) -> Egg Shop|Small | K43: Cash
A44: 46113 | B44: Egg Shop | C44: Pullet 1 | D44: 4 | E44: 40 | F44: 40 | G44: =IF(OR(D44="",E44=""),"",D44*E44) -> 160 | H44: =IF(OR(D44="",F44=""),"",D44*F44) -> 160 | I44: =IF(OR(G44="",H44=""),"",G44-H44) -> 0 | J44: =IF(OR(B44="",C44=""),"",B44&"|"&C44) -> Egg Shop|Pullet 1 | K44: Cash
A45: 46113 | B45: Egg Shop | C45: Pullet 2 | D45: 0 | E45: 35 | F45: 35 | G45: =IF(OR(D45="",E45=""),"",D45*E45) -> 0 | H45: =IF(OR(D45="",F45=""),"",D45*F45) -> 0 | I45: =IF(OR(G45="",H45=""),"",G45-H45) -> 0 | J45: =IF(OR(B45="",C45=""),"",B45&"|"&C45) -> Egg Shop|Pullet 2 | K45: Cash
A46: 46113 | B46: Egg Shop | C46: Broken | D46: 2 | E46: 30 | F46: 30 | G46: =IF(OR(D46="",E46=""),"",D46*E46) -> 60 | H46: =IF(OR(D46="",F46=""),"",D46*F46) -> 60 | I46: =IF(OR(G46="",H46=""),"",G46-H46) -> 0 | J46: =IF(OR(B46="",C46=""),"",B46&"|"&C46) -> Egg Shop|Broken | K46: Cash
A47: 46114 | B47: Egg Shop | C47: Small | D47: 4 | E47: 55 | F47: 55 | G47: =IF(OR(D47="",E47=""),"",D47*E47) -> 220 | H47: =IF(OR(D47="",F47=""),"",D47*F47) -> 220 | I47: =IF(OR(G47="",H47=""),"",G47-H47) -> 0 | J47: =IF(OR(B47="",C47=""),"",B47&"|"&C47) -> Egg Shop|Small | K47: Cash
A48: 46114 | B48: Egg Shop | C48: Pullet 1 | D48: 1 | E48: 40 | F48: 40 | G48: =IF(OR(D48="",E48=""),"",D48*E48) -> 40 | H48: =IF(OR(D48="",F48=""),"",D48*F48) -> 40 | I48: =IF(OR(G48="",H48=""),"",G48-H48) -> 0 | J48: =IF(OR(B48="",C48=""),"",B48&"|"&C48) -> Egg Shop|Pullet 1 | K48: Cash
A49: 46115 | B49: Egg Shop | C49: Large | D49: 13 | E49: 60 | F49: 60 | G49: =IF(OR(D49="",E49=""),"",D49*E49) -> 780 | H49: =IF(OR(D49="",F49=""),"",D49*F49) -> 780 | I49: =IF(OR(G49="",H49=""),"",G49-H49) -> 0 | J49: =IF(OR(B49="",C49=""),"",B49&"|"&C49) -> Egg Shop|Large | K49: Cash
A50: 46115 | B50: Egg Shop | C50: Medium | D50: 55 | E50: 58 | F50: 58 | G50: =IF(OR(D50="",E50=""),"",D50*E50) -> 3190 | H50: =IF(OR(D50="",F50=""),"",D50*F50) -> 3190 | I50: =IF(OR(G50="",H50=""),"",G50-H50) -> 0 | J50: =IF(OR(B50="",C50=""),"",B50&"|"&C50) -> Egg Shop|Medium | K50: Cash
A51: 46115 | B51: Egg Shop | C51: Small | D51: 85 | E51: 55 | F51: 55 | G51: =IF(OR(D51="",E51=""),"",D51*E51) -> 4675 | H51: =IF(OR(D51="",F51=""),"",D51*F51) -> 4675 | I51: =IF(OR(G51="",H51=""),"",G51-H51) -> 0 | J51: =IF(OR(B51="",C51=""),"",B51&"|"&C51) -> Egg Shop|Small | K51: Cash
A52: 46115 | B52: Egg Shop | C52: Pullet 1 | D52: 126 | E52: 40 | F52: 40 | G52: =IF(OR(D52="",E52=""),"",D52*E52) -> 5040 | H52: =IF(OR(D52="",F52=""),"",D52*F52) -> 5040 | I52: =IF(OR(G52="",H52=""),"",G52-H52) -> 0 | J52: =IF(OR(B52="",C52=""),"",B52&"|"&C52) -> Egg Shop|Pullet 1 | K52: Cash
... A85: 46123 | B85: Egg Shop | C85: Broken | D85: -7 | E85: 30 | F85: 30 | G85: =IF(OR(D85="",E85=""),"",D85*E85) -> -210 | H85: =IF(OR(D85="",F85=""),"",D85*F85) -> -210 | I85: =IF(OR(G85="",H85=""),"",G85-H85) -> 0 | J85: =IF(OR(B85="",C85=""),"",B85&"|"&C85) -> Egg Shop|Broken | K85: Cash
A86: 46123 | B86: Akatsi Feed | C86: LM | D86: 6 | E86: 365 | F86: =IF(B86="Egg Shop","",IF(J86="","",IFERROR(LOOKUP(2,1/(Purchases!$H$3:$H$2002=J86),Purchases!$F$3:$F$2002),""))) -> 352 | G86: =IF(OR(D86="",E86=""),"",D86*E86) -> 2190 | H86: =IF(OR(D86="",F86=""),"",D86*F86) -> 2112 | I86: =IF(OR(G86="",H86=""),"",G86-H86) -> 78 | J86: =IF(OR(B86="",C86=""),"",B86&"|"&C86) -> Akatsi Feed|LM | K86: Cash
A87: 46123 | B87: Akatsi Feed | C87: GM | D87: 2 | E87: 350 | F87: =IF(B87="Egg Shop","",IF(J87="","",IFERROR(LOOKUP(2,1/(Purchases!$H$3:$H$2002=J87),Purchases!$F$3:$F$2002),""))) -> 340 | G87: =IF(OR(D87="",E87=""),"",D87*E87) -> 700 | H87: =IF(OR(D87="",F87=""),"",D87*F87) -> 680 | I87: =IF(OR(G87="",H87=""),"",G87-H87) -> 20 | J87: =IF(OR(B87="",C87=""),"",B87&"|"&C87) -> Akatsi Feed|GM | K87: Cash
A88: 46123 | B88: Akatsi Feed | C88: CM | D88: 1 | E88: 370 | F88: =IF(B88="Egg Shop","",IF(J88="","",IFERROR(LOOKUP(2,1/(Purchases!$H$3:$H$2002=J88),Purchases!$F$3:$F$2002),""))) -> 357 | G88: =IF(OR(D88="",E88=""),"",D88*E88) -> 370 | H88: =IF(OR(D88="",F88=""),"",D88*F88) -> 357 | I88: =IF(OR(G88="",H88=""),"",G88-H88) -> 13 | J88: =IF(OR(B88="",C88=""),"",B88&"|"&C88) -> Akatsi Feed|CM | K88: Cash
A89: 46123 | B89: Akatsi Feed | C89: Crates | D89: 1 | E89: 90 | F89: =IF(B89="Egg Shop","",IF(J89="","",IFERROR(LOOKUP(2,1/(Purchases!$H$3:$H$2002=J89),Purchases!$F$3:$F$2002),""))) -> 80 | G89: =IF(OR(D89="",E89=""),"",D89*E89) -> 90 | H89: =IF(OR(D89="",F89=""),"",D89*F89) -> 80 | I89: =IF(OR(G89="",H89=""),"",G89-H89) -> 10 | J89: =IF(OR(B89="",C89=""),"",B89&"|"&C89) -> Akatsi Feed|Crates | K89: Cash
A90: 46123 | B90: Abor Feed | C90: LM | D90: 3 | E90: 365 | F90: =IF(B90="Egg Shop","",IF(J90="","",IFERROR(LOOKUP(2,1/(Purchases!$H$3:$H$2002=J90),Purchases!$F$3:$F$2002),""))) -> 352 | G90: =IF(OR(D90="",E90=""),"",D90*E90) -> 1095 | H90: =IF(OR(D90="",F90=""),"",D90*F90) -> 1056 | I90: =IF(OR(G90="",H90=""),"",G90-H90) -> 39 | J90: =IF(OR(B90="",C90=""),"",B90&"|"&C90) -> Abor Feed|LM | K90: Cash
A91: 46125 | B91: Akatsi Feed | C91: LM | D91: 9 | E91: 365 | F91: =IF(B91="Egg Shop","",IF(J91="","",IFERROR(LOOKUP(2,1/(Purchases!$H$3:$H$2002=J91),Purchases!$F$3:$F$2002),""))) -> 352 | G91: =IF(OR(D91="",E91=""),"",D91*E91) -> 3285 | H91: =IF(OR(D91="",F91=""),"",D91*F91) -> 3168 | I91: =IF(OR(G91="",H91=""),"",G91-H91) -> 117 | J91: =IF(OR(B91="",C91=""),"",B91&"|"&C91) -> Akatsi Feed|LM | K91: Cash
A92: 46125 | B92: Akatsi Feed | C92: GM | D92: 2 | E92: 350 | F92: =IF(B92="Egg Shop","",IF(J92="","",IFERROR(LOOKUP(2,1/(Purchases!$H$3:$H$2002=J92),Purchases!$F$3:$F$2002),""))) -> 340 | G92: =IF(OR(D92="",E92=""),"",D92*E92) -> 700 | H92: =IF(OR(D92="",F92=""),"",D92*F92) -> 680 | I92: =IF(OR(G92="",H92=""),"",G92-H92) -> 20 | J92: =IF(OR(B92="",C92=""),"",B92&"|"&C92) -> Akatsi Feed|GM | K92: Cash
A93: 46125 | B93: Akatsi Feed | C93: CM | D93: 0 | E93: 370 | F93: =IF(B93="Egg Shop","",IF(J93="","",IFERROR(LOOKUP(2,1/(Purchases!$H$3:$H$2002=J93),Purchases!$F$3:$F$2002),""))) -> 357 | G93: =IF(OR(D93="",E93=""),"",D93*E93) -> 0 | H93: =IF(OR(D93="",F93=""),"",D93*F93) -> 0 | I93: =IF(OR(G93="",H93=""),"",G93-H93) -> 0 | J93: =IF(OR(B93="",C93=""),"",B93&"|"&C93) -> Akatsi Feed|CM | K93: Cash
A94: 46125 | B94: Akatsi Feed | C94: Crates | D94: 8 | E94: 90 | F94: =IF(B94="Egg Shop","",IF(J94="","",IFERROR(LOOKUP(2,1/(Purchases!$H$3:$H$2002=J94),Purchases!$F$3:$F$2002),""))) -> 80 | G94: =IF(OR(D94="",E94=""),"",D94*E94) -> 720 | H94: =IF(OR(D94="",F94=""),"",D94*F94) -> 640 | I94: =IF(OR(G94="",H94=""),"",G94-H94) -> 80 | J94: =IF(OR(B94="",C94=""),"",B94&"|"&C94) -> Akatsi Feed|Crates | K94: Cash
A95: 46125 | B95: Abor Feed | C95: LM | D95: 1 | E95: 365 | F95: =IF(B95="Egg Shop","",IF(J95="","",IFERROR(LOOKUP(2,1/(Purchases!$H$3:$H$2002=J95),Purchases!$F$3:$F$2002),""))) -> 352 | G95: =IF(OR(D95="",E95=""),"",D95*E95) -> 365 | H95: =IF(OR(D95="",F95=""),"",D95*F95) -> 352 | I95: =IF(OR(G95="",H95=""),"",G95-H95) -> 13 | J95: =IF(OR(B95="",C95=""),"",B95&"|"&C95) -> Abor Feed|LM | K95: Cash
A96: 46125 | B96: Egg Shop | C96: Large | D96: 0 | E96: 60 | F96: 60 | G96: =IF(OR(D96="",E96=""),"",D96*E96) -> 0 | H96: =IF(OR(D96="",F96=""),"",D96*F96) -> 0 | I96: =IF(OR(G96="",H96=""),"",G96-H96) -> 0 | J96: =IF(OR(B96="",C96=""),"",B96&"|"&C96) -> Egg Shop|Large | K96: Cash
A97: 46125 | B97: Egg Shop | C97: Medium | D97: 1 | E97: 58 | F97: 58 | G97: =IF(OR(D97="",E97=""),"",D97*E97) -> 58 | H97: =IF(OR(D97="",F97=""),"",D97*F97) -> 58 | I97: =IF(OR(G97="",H97=""),"",G97-H97) -> 0 | J97: =IF(OR(B97="",C97=""),"",B97&"|"&C97) -> Egg Shop|Medium | K97: Cash
A98: 46125 | B98: Egg Shop | C98: Small | D98: 2 | E98: 55 | F98: 55 | G98: =IF(OR(D98="",E98=""),"",D98*E98) -> 110 | H98: =IF(OR(D98="",F98=""),"",D98*F98) -> 110 | I98: =IF(OR(G98="",H98=""),"",G98-H98) -> 0 | J98: =IF(OR(B98="",C98=""),"",B98&"|"&C98) -> Egg Shop|Small | K98: Cash
A99: 46125 | B99: Egg Shop | C99: Pullet 1 | D99: 0 | E99: 40 | F99: 40 | G99: =IF(OR(D99="",E99=""),"",D99*E99) -> 0 | H99: =IF(OR(D99="",F99=""),"",D99*F99) -> 0 | I99: =IF(OR(G99="",H99=""),"",G99-H99) -> 0 | J99: =IF(OR(B99="",C99=""),"",B99&"|"&C99) -> Egg Shop|Pullet 1 | K99: Cash
A100: 46125 | B100: Egg Shop | C100: Pullet 2 | D100: 0 | E100: 35 | F100: 35 | G100: =IF(OR(D100="",E100=""),"",D100*E100) -> 0 | H100: =IF(OR(D100="",F100=""),"",D100*F100) -> 0 | I100: =IF(OR(G100="",H100=""),"",G100-H100) -> 0 | J100: =IF(OR(B100="",C100=""),"",B100&"|"&C100) -> Egg Shop|Pullet 2 | K100: Cash
A101: 46125 | B101: Egg Shop | C101: Broken | D101: 3 | E101: 30 | F101: 30 | G101: =IF(OR(D101="",E101=""),"",D101*E101) -> 90 | H101: =IF(OR(D101="",F101=""),"",D101*F101) -> 90 | I101: =IF(OR(G101="",H101=""),"",G101-H101) -> 0 | J101: =IF(OR(B101="",C101=""),"",B101&"|"&C101) -> Egg Shop|Broken | K101: Cash
A102: 46126 | B102: Akatsi Feed | C102: LM | D102: 3 | E102: 365 | F102: =IF(B102="Egg Shop","",IF(J102="","",IFERROR(LOOKUP(2,1/(Purchases!$H$3:$H$2002=J102),Purchases!$F$3:$F$2002),""))) -> 352 | G102: =IF(OR(D102="",E102=""),"",D102*E102) -> 1095 | H102: =IF(OR(D102="",F102=""),"",D102*F102) -> 1056 | I102: =IF(OR(G102="",H102=""),"",G102-H102) -> 39 | J102: =IF(OR(B102="",C102=""),"",B102&"|"&C102) -> Akatsi Feed|LM | K102: Cash
A103: 46126 | B103: Akatsi Feed | C103: GM | D103: 2 | E103: 350 | F103: =IF(B103="Egg Shop","",IF(J103="","",IFERROR(LOOKUP(2,1/(Purchases!$H$3:$H$2002=J103),Purchases!$F$3:$F$2002),""))) -> 340 | G103: =IF(OR(D103="",E103=""),"",D103*E103) -> 700 | H103: =IF(OR(D103="",F103=""),"",D103*F103) -> 680 | I103: =IF(OR(G103="",H103=""),"",G103-H103) -> 20 | J103: =IF(OR(B103="",C103=""),"",B103&"|"&C103) -> Akatsi Feed|GM | K103: Cash
A104: 46126 | B104: Akatsi Feed | C104: CM | D104: 0 | E104: 370 | F104: =IF(B104="Egg Shop","",IF(J104="","",IFERROR(LOOKUP(2,1/(Purchases!$H$3:$H$2002=J104),Purchases!$F$3:$F$2002),""))) -> 357 | G104: =IF(OR(D104="",E104=""),"",D104*E104) -> 0 | H104: =IF(OR(D104="",F104=""),"",D104*F104) -> 0 | I104: =IF(OR(G104="",H104=""),"",G104-H104) -> 0 | J104: =IF(OR(B104="",C104=""),"",B104&"|"&C104) -> Akatsi Feed|CM | K104: Cash
A105: 46126 | B105: Akatsi Feed | C105: Crates | D105: 0 | E105: 90 | F105: =IF(B105="Egg Shop","",IF(J105="","",IFERROR(LOOKUP(2,1/(Purchases!$H$3:$H$2002=J105),Purchases!$F$3:$F$2002),""))) -> 80 | G105: =IF(OR(D105="",E105=""),"",D105*E105) -> 0 | H105: =IF(OR(D105="",F105=""),"",D105*F105) -> 0 | I105: =IF(OR(G105="",H105=""),"",G105-H105) -> 0 | J105: =IF(OR(B105="",C105=""),"",B105&"|"&C105) -> Akatsi Feed|Crates | K105: Cash
A106: 46126 | B106: Abor Feed | C106: LM | D106: 6 | E106: 365 | F106: =IF(B106="Egg Shop","",IF(J106="","",IFERROR(LOOKUP(2,1/(Purchases!$H$3:$H$2002=J106),Purchases!$F$3:$F$2002),""))) -> 352 | G106: =IF(OR(D106="",E106=""),"",D106*E106) -> 2190 | H106: =IF(OR(D106="",F106=""),"",D106*F106) -> 2112 | I106: =IF(OR(G106="",H106=""),"",G106-H106) -> 78 | J106: =IF(OR(B106="",C106=""),"",B106&"|"&C106) -> Abor Feed|LM | K106: Cash
A107: 46126 | B107: Abor Feed | C107: GM | D107: 1 | E107: 350 | F107: =IF(B107="Egg Shop","",IF(J107="","",IFERROR(LOOKUP(2,1/(Purchases!$H$3:$H$2002=J107),Purchases!$F$3:$F$2002),""))) -> 340 | G107: =IF(OR(D107="",E107=""),"",D107*E107) -> 350 | H107: =IF(OR(D107="",F107=""),"",D107*F107) -> 340 | I107: =IF(OR(G107="",H107=""),"",G107-H107) -> 10 | J107: =IF(OR(B107="",C107=""),"",B107&"|"&C107) -> Abor Feed|GM | K107: Cash
A108: 46126 | B108: Egg Shop | C108: Medium | D108: 5 | E108: 58 | F108: 58 | G108: =IF(OR(D108="",E108=""),"",D108*E108) -> 290 | H108: =IF(OR(D108="",F108=""),"",D108*F108) -> 290 | I108: =IF(OR(G108="",H108=""),"",G108-H108) -> 0 | J108: =IF(OR(B108="",C108=""),"",B108&"|"&C108) -> Egg Shop|Medium | K108: Cash
A109: 46126 | B109: Egg Shop | C109: Small | D109: 3.5 | E109: 55 | F109: 55 | G109: =IF(OR(D109="",E109=""),"",D109*E109) -> 192.5 | H109: =IF(OR(D109="",F109=""),"",D109*F109) -> 192.5 | I109: =IF(OR(G109="",H109=""),"",G109-H109) -> 0 | J109: =IF(OR(B109="",C109=""),"",B109&"|"&C109) -> Egg Shop|Small | K109: Cash
A110: 46126 | B110: Egg Shop | C110: Pullet 1 | D110: 0 | E110: 40 | F110: 40 | G110: =IF(OR(D110="",E110=""),"",D110*E110) -> 0 | H110: =IF(OR(D110="",F110=""),"",D110*F110) -> 0 | I110: =IF(OR(G110="",H110=""),"",G110-H110) -> 0 | J110: =IF(OR(B110="",C110=""),"",B110&"|"&C110) -> Egg Shop|Pullet 1 | K110: Cash
A111: 46126 | B111: Egg Shop | C111: Pullet 2 | D111: 0 | E111: 35 | F111: 35 | G111: =IF(OR(D111="",E111=""),"",D111*E111) -> 0 | H111: =IF(OR(D111="",F111=""),"",D111*F111) -> 0 | I111: =IF(OR(G111="",H111=""),"",G111-H111) -> 0 | J111: =IF(OR(B111="",C111=""),"",B111&"|"&C111) -> Egg Shop|Pullet 2 | K111: Cash
A112: 46126 | B112: Egg Shop | C112: Broken | D112: 0 | E112: 30 | F112: 30 | G112: =IF(OR(D112="",E112=""),"",D112*E112) -> 0 | H112: =IF(OR(D112="",F112=""),"",D112*F112) -> 0 | I112: =IF(OR(G112="",H112=""),"",G112-H112) -> 0 | J112: =IF(OR(B112="",C112=""),"",B112&"|"&C112) -> Egg Shop|Broken | K112: Cash
A113: 46127 | B113: Akatsi Feed | C113: LM | D113: 3 | E113: 365 | F113: =IF(B113="Egg Shop","",IF(J113="","",IFERROR(LOOKUP(2,1/(Purchases!$H$3:$H$2002=J113),Purchases!$F$3:$F$2002),""))) -> 352 | G113: =IF(OR(D113="",E113=""),"",D113*E113) -> 1095 | H113: =IF(OR(D113="",F113=""),"",D113*F113) -> 1056 | I113: =IF(OR(G113="",H113=""),"",G113-H113) -> 39 | J113: =IF(OR(B113="",C113=""),"",B113&"|"&C113) -> Akatsi Feed|LM | K113: Cash
A114: 46128 | B114: Abor Feed | C114: LM | D114: 5 | E114: 365 | F114: =IF(B114="Egg Shop","",IF(J114="","",IFERROR(LOOKUP(2,1/(Purchases!$H$3:$H$2002=J114),Purchases!$F$3:$F$2002),""))) -> 352 | G114: =IF(OR(D114="",E114=""),"",D114*E114) -> 1825 | H114: =IF(OR(D114="",F114=""),"",D114*F114) -> 1760 | I114: =IF(OR(G114="",H114=""),"",G114-H114) -> 65 | J114: =IF(OR(B114="",C114=""),"",B114&"|"&C114) -> Abor Feed|LM | K114: Cash
A115: 46128 | B115: Akatsi Feed | C115: LM | D115: 5 | E115: 365 | F115: =IF(B115="Egg Shop","",IF(J115="","",IFERROR(LOOKUP(2,1/(Purchases!$H$3:$H$2002=J115),Purchases!$F$3:$F$2002),""))) -> 352 | G115: =IF(OR(D115="",E115=""),"",D115*E115) -> 1825 | H115: =IF(OR(D115="",F115=""),"",D115*F115) -> 1760 | I115: =IF(OR(G115="",H115=""),"",G115-H115) -> 65 | J115: =IF(OR(B115="",C115=""),"",B115&"|"&C115) -> Akatsi Feed|LM | K115: Cash
A116: 46128 | B116: Akatsi Feed | C116: GM | D116: 1 | E116: 350 | F116: =IF(B116="Egg Shop","",IF(J116="","",IFERROR(LOOKUP(2,1/(Purchases!$H$3:$H$2002=J116),Purchases!$F$3:$F$2002),""))) -> 340 | G116: =IF(OR(D116="",E116=""),"",D116*E116) -> 350 | H116: =IF(OR(D116="",F116=""),"",D116*F116) -> 340 | I116: =IF(OR(G116="",H116=""),"",G116-H116) -> 10 | J116: =IF(OR(B116="",C116=""),"",B116&"|"&C116) -> Akatsi Feed|GM | K116: Cash
A117: 46128 | B117: Akatsi Feed | C117: CM | D117: 1 | E117: 370 | F117: =IF(B117="Egg Shop","",IF(J117="","",IFERROR(LOOKUP(2,1/(Purchases!$H$3:$H$2002=J117),Purchases!$F$3:$F$2002),""))) -> 357 | G117: =IF(OR(D117="",E117=""),"",D117*E117) -> 370 | H117: =IF(OR(D117="",F117=""),"",D117*F117) -> 357 | I117: =IF(OR(G117="",H117=""),"",G117-H117) -> 13 | J117: =IF(OR(B117="",C117=""),"",B117&"|"&C117) -> Akatsi Feed|CM | K117: Cash
A118: 46128 | B118: Akatsi Feed | C118: Crates | D118: 0 | E118: 90 | F118: =IF(B118="Egg Shop","",IF(J118="","",IFERROR(LOOKUP(2,1/(Purchases!$H$3:$H$2002=J118),Purchases!$F$3:$F$2002),""))) -> 80 | G118: =IF(OR(D118="",E118=""),"",D118*E118) -> 0 | H118: =IF(OR(D118="",F118=""),"",D118*F118) -> 0 | I118: =IF(OR(G118="",H118=""),"",G118-H118) -> 0 | J118: =IF(OR(B118="",C118=""),"",B118&"|"&C118) -> Akatsi Feed|Crates | K118: Cash
A119: 46129 | B119: Abor Feed | C119: LM | D119: 4 | E119: 365 | F119: =IF(B119="Egg Shop","",IF(J119="","",IFERROR(LOOKUP(2,1/(Purchases!$H$3:$H$2002=J119),Purchases!$F$3:$F$2002),""))) -> 352 | G119: =IF(OR(D119="",E119=""),"",D119*E119) -> 1460 | H119: =IF(OR(D119="",F119=""),"",D119*F119) -> 1408 | I119: =IF(OR(G119="",H119=""),"",G119-H119) -> 52 | J119: =IF(OR(B119="",C119=""),"",B119&"|"&C119) -> Abor Feed|LM | K119: Cash
A120: 46130 | B120: Abor Feed | C120: LM | D120: 10 | E120: 365 | F120: =IF(B120="Egg Shop","",IF(J120="","",IFERROR(LOOKUP(2,1/(Purchases!$H$3:$H$2002=J120),Purchases!$F$3:$F$2002),""))) -> 352 | G120: =IF(OR(D120="",E120=""),"",D120*E120) -> 3650 | H120: =IF(OR(D120="",F120=""),"",D120*F120) -> 3520 | I120: =IF(OR(G120="",H120=""),"",G120-H120) -> 130 | J120: =IF(OR(B120="",C120=""),"",B120&"|"&C120) -> Abor Feed|LM | K120: Cash
A121: 46132 | B121: Abor Feed | C121: GM | D121: 1 | E121: 355 | F121: =IF(B121="Egg Shop","",IF(J121="","",IFERROR(LOOKUP(2,1/(Purchases!$H$3:$H$2002=J121),Purchases!$F$3:$F$2002),""))) -> 340 | G121: =IF(OR(D121="",E121=""),"",D121*E121) -> 355 | H121: =IF(OR(D121="",F121=""),"",D121*F121) -> 340 | I121: =IF(OR(G121="",H121=""),"",G121-H121) -> 15 | J121: =IF(OR(B121="",C121=""),"",B121&"|"&C121) -> Abor Feed|GM | K121: Cash
A122: 46133 | B122: Abor Feed | C122: LM | D122: 2 | E122: 365 | F122: =IF(B122="Egg Shop","",IF(J122="","",IFERROR(LOOKUP(2,1/(Purchases!$H$3:$H$2002=J122),Purchases!$F$3:$F$2002),""))) -> 352 | G122: =IF(OR(D122="",E122=""),"",D122*E122) -> 730 | H122: =IF(OR(D122="",F122=""),"",D122*F122) -> 704 | I122: =IF(OR(G122="",H122=""),"",G122-H122) -> 26 | J122: =IF(OR(B122="",C122=""),"",B122&"|"&C122) -> Abor Feed|LM | K122: Cash
A123: 46133 | B123: Abor Feed | C123: GM | D123: 2 | E123: 355 | F123: =IF(B123="Egg Shop","",IF(J123="","",IFERROR(LOOKUP(2,1/(Purchases!$H$3:$H$2002=J123),Purchases!$F$3:$F$2002),""))) -> 340 | G123: =IF(OR(D123="",E123=""),"",D123*E123) -> 710 | H123: =IF(OR(D123="",F123=""),"",D123*F123) -> 680 | I123: =IF(OR(G123="",H123=""),"",G123-H123) -> 30 | J123: =IF(OR(B123="",C123=""),"",B123&"|"&C123) -> Abor Feed|GM | K123: Cash
A124: 46134 | B124: Abor Feed | C124: LM | D124: 2 | E124: 365 | F124: =IF(B124="Egg Shop","",IF(J124="","",IFERROR(LOOKUP(2,1/(Purchases!$H$3:$H$2002=J124),Purchases!$F$3:$F$2002),""))) -> 352 | G124: =IF(OR(D124="",E124=""),"",D124*E124) -> 730 | H124: =IF(OR(D124="",F124=""),"",D124*F124) -> 704 | I124: =IF(OR(G124="",H124=""),"",G124-H124) -> 26 | J124: =IF(OR(B124="",C124=""),"",B124&"|"&C124) -> Abor Feed|LM | K124: Cash
... A145: 46136 | B145: Akatsi Feed | C145: GM | D145: 1 | E145: 350 | F145: =IF(B145="Egg Shop","",IF(J145="","",IFERROR(LOOKUP(2,1/(Purchases!$H$3:$H$2002=J145),Purchases!$F$3:$F$2002),""))) -> 340 | G145: =IF(OR(D145="",E145=""),"",D145*E145) -> 350 | H145: =IF(OR(D145="",F145=""),"",D145*F145) -> 340 | I145: =IF(OR(G145="",H145=""),"",G145-H145) -> 10 | J145: =IF(OR(B145="",C145=""),"",B145&"|"&C145) -> Akatsi Feed|GM | K145: Cash
A146: 46136 | B146: Akatsi Feed | C146: CM | D146: 1 | E146: 370 | F146: =IF(B146="Egg Shop","",IF(J146="","",IFERROR(LOOKUP(2,1/(Purchases!$H$3:$H$2002=J146),Purchases!$F$3:$F$2002),""))) -> 357 | G146: =IF(OR(D146="",E146=""),"",D146*E146) -> 370 | H146: =IF(OR(D146="",F146=""),"",D146*F146) -> 357 | I146: =IF(OR(G146="",H146=""),"",G146-H146) -> 13 | J146: =IF(OR(B146="",C146=""),"",B146&"|"&C146) -> Akatsi Feed|CM | K146: =IF(A146<>"","Cash","") -> Cash
A147: 46136 | B147: Akatsi Feed | C147: Crates | D147: 1 | E147: 90 | F147: =IF(B147="Egg Shop","",IF(J147="","",IFERROR(LOOKUP(2,1/(Purchases!$H$3:$H$2002=J147),Purchases!$F$3:$F$2002),""))) -> 80 | G147: =IF(OR(D147="",E147=""),"",D147*E147) -> 90 | H147: =IF(OR(D147="",F147=""),"",D147*F147) -> 80 | I147: =IF(OR(G147="",H147=""),"",G147-H147) -> 10 | J147: =IF(OR(B147="",C147=""),"",B147&"|"&C147) -> Akatsi Feed|Crates | K147: =IF(A147<>"","Cash","") -> Cash
A148: 46137 | B148: Akatsi Feed | C148: LM | D148: 15 | E148: 365 | F148: =IF(B148="Egg Shop","",IF(J148="","",IFERROR(LOOKUP(2,1/(Purchases!$H$3:$H$2002=J148),Purchases!$F$3:$F$2002),""))) -> 352 | G148: =IF(OR(D148="",E148=""),"",D148*E148) -> 5475 | H148: =IF(OR(D148="",F148=""),"",D148*F148) -> 5280 | I148: =IF(OR(G148="",H148=""),"",G148-H148) -> 195 | J148: =IF(OR(B148="",C148=""),"",B148&"|"&C148) -> Akatsi Feed|LM | K148: =IF(A148<>"","Cash","") -> Cash
A149: 46137 | B149: Akatsi Feed | C149: GM | D149: 7 | E149: 350 | F149: =IF(B149="Egg Shop","",IF(J149="","",IFERROR(LOOKUP(2,1/(Purchases!$H$3:$H$2002=J149),Purchases!$F$3:$F$2002),""))) -> 340 | G149: =IF(OR(D149="",E149=""),"",D149*E149) -> 2450 | H149: =IF(OR(D149="",F149=""),"",D149*F149) -> 2380 | I149: =IF(OR(G149="",H149=""),"",G149-H149) -> 70 | J149: =IF(OR(B149="",C149=""),"",B149&"|"&C149) -> Akatsi Feed|GM | K149: =IF(A149<>"","Cash","") -> Cash
A150: 46137 | B150: Abor Feed | C150: LM | D150: 4 | E150: 365 | F150: =IF(B150="Egg Shop","",IF(J150="","",IFERROR(LOOKUP(2,1/(Purchases!$H$3:$H$2002=J150),Purchases!$F$3:$F$2002),""))) -> 352 | G150: =IF(OR(D150="",E150=""),"",D150*E150) -> 1460 | H150: =IF(OR(D150="",F150=""),"",D150*F150) -> 1408 | I150: =IF(OR(G150="",H150=""),"",G150-H150) -> 52 | J150: =IF(OR(B150="",C150=""),"",B150&"|"&C150) -> Abor Feed|LM | K150: =IF(A150<>"","Cash","") -> Cash
A151: 46139 | B151: Akatsi Feed | C151: LM | D151: 25 | E151: 365 | F151: =IF(B151="Egg Shop","",IF(J151="","",IFERROR(LOOKUP(2,1/(Purchases!$H$3:$H$2002=J151),Purchases!$F$3:$F$2002),""))) -> 352 | G151: =IF(OR(D151="",E151=""),"",D151*E151) -> 9125 | H151: =IF(OR(D151="",F151=""),"",D151*F151) -> 8800 | I151: =IF(OR(G151="",H151=""),"",G151-H151) -> 325 | J151: =IF(OR(B151="",C151=""),"",B151&"|"&C151) -> Akatsi Feed|LM | K151: =IF(A151<>"","Cash","") -> Cash
A152: 46139 | B152: Akatsi Feed | C152: GM | D152: 5 | E152: 350 | F152: =IF(B152="Egg Shop","",IF(J152="","",IFERROR(LOOKUP(2,1/(Purchases!$H$3:$H$2002=J152),Purchases!$F$3:$F$2002),""))) -> 340 | G152: =IF(OR(D152="",E152=""),"",D152*E152) -> 1750 | H152: =IF(OR(D152="",F152=""),"",D152*F152) -> 1700 | I152: =IF(OR(G152="",H152=""),"",G152-H152) -> 50 | J152: =IF(OR(B152="",C152=""),"",B152&"|"&C152) -> Akatsi Feed|GM | K152: =IF(A152<>"","Cash","") -> Cash
A153: 46139 | B153: Akatsi Feed | C153: Crates | D153: 3 | E153: 90 | F153: =IF(B153="Egg Shop","",IF(J153="","",IFERROR(LOOKUP(2,1/(Purchases!$H$3:$H$2002=J153),Purchases!$F$3:$F$2002),""))) -> 80 | G153: =IF(OR(D153="",E153=""),"",D153*E153) -> 270 | H153: =IF(OR(D153="",F153=""),"",D153*F153) -> 240 | I153: =IF(OR(G153="",H153=""),"",G153-H153) -> 30 | J153: =IF(OR(B153="",C153=""),"",B153&"|"&C153) -> Akatsi Feed|Crates | K153: =IF(A153<>"","Cash","") -> Cash
A154: 46139 | B154: Abor Feed | C154: LM | D154: 4 | E154: 365 | F154: =IF(B154="Egg Shop","",IF(J154="","",IFERROR(LOOKUP(2,1/(Purchases!$H$3:$H$2002=J154),Purchases!$F$3:$F$2002),""))) -> 352 | G154: =IF(OR(D154="",E154=""),"",D154*E154) -> 1460 | H154: =IF(OR(D154="",F154=""),"",D154*F154) -> 1408 | I154: =IF(OR(G154="",H154=""),"",G154-H154) -> 52 | J154: =IF(OR(B154="",C154=""),"",B154&"|"&C154) -> Abor Feed|LM | K154: =IF(A154<>"","Cash","") -> Cash
A155: 46140 | B155: Akatsi Feed | C155: LM | D155: 4 | E155: 365 | F155: =IF(B155="Egg Shop","",IF(J155="","",IFERROR(LOOKUP(2,1/(Purchases!$H$3:$H$2002=J155),Purchases!$F$3:$F$2002),""))) -> 352 | G155: =IF(OR(D155="",E155=""),"",D155*E155) -> 1460 | H155: =IF(OR(D155="",F155=""),"",D155*F155) -> 1408 | I155: =IF(OR(G155="",H155=""),"",G155-H155) -> 52 | J155: =IF(OR(B155="",C155=""),"",B155&"|"&C155) -> Akatsi Feed|LM | K155: =IF(A155<>"","Cash","") -> Cash
A156: 46140 | B156: Akatsi Feed | C156: GM | D156: 2 | E156: 350 | F156: =IF(B156="Egg Shop","",IF(J156="","",IFERROR(LOOKUP(2,1/(Purchases!$H$3:$H$2002=J156),Purchases!$F$3:$F$2002),""))) -> 340 | G156: =IF(OR(D156="",E156=""),"",D156*E156) -> 700 | H156: =IF(OR(D156="",F156=""),"",D156*F156) -> 680 | I156: =IF(OR(G156="",H156=""),"",G156-H156) -> 20 | J156: =IF(OR(B156="",C156=""),"",B156&"|"&C156) -> Akatsi Feed|GM | K156: =IF(A156<>"","Cash","") -> Cash
A157: 46140 | B157: Akatsi Feed | C157: CM | D157: 1 | E157: 370 | F157: =IF(B157="Egg Shop","",IF(J157="","",IFERROR(LOOKUP(2,1/(Purchases!$H$3:$H$2002=J157),Purchases!$F$3:$F$2002),""))) -> 357 | G157: =IF(OR(D157="",E157=""),"",D157*E157) -> 370 | H157: =IF(OR(D157="",F157=""),"",D157*F157) -> 357 | I157: =IF(OR(G157="",H157=""),"",G157-H157) -> 13 | J157: =IF(OR(B157="",C157=""),"",B157&"|"&C157) -> Akatsi Feed|CM | K157: =IF(A157<>"","Cash","") -> Cash
... A179: 46142 | B179: Mobile Shop | C179: LM | D179: 8 | E179: 357 | F179: =IF(B179="Egg Shop","",IF(J179="","",IFERROR(LOOKUP(2,1/(Purchases!$H$3:$H$2002=J179),Purchases!$F$3:$F$2002),""))) -> 352 | G179: =IF(OR(D179="",E179=""),"",D179*E179) -> 2856 | H179: =IF(OR(D179="",F179=""),"",D179*F179) -> 2816 | I179: =IF(OR(G179="",H179=""),"",G179-H179) -> 40 | J179: =IF(OR(B179="",C179=""),"",B179&"|"&C179) -> Mobile Shop|LM | K179: =IF(A179<>"","Cash","") -> Cash
A180: 46127 | B180: Egg Shop | C180: Large | D180: 0 | E180: 60 | F180: 60 | G180: =IF(OR(D180="",E180=""),"",D180*E180) -> 0 | H180: =IF(OR(D180="",F180=""),"",D180*F180) -> 0 | I180: =IF(OR(G180="",H180=""),"",G180-H180) -> 0 | J180: =IF(OR(B180="",C180=""),"",B180&"|"&C180) -> Egg Shop|Large | K180: =IF(A180<>"","Cash","") -> Cash
A181: 46127 | B181: Egg Shop | C181: Medium | D181: 29 | E181: 58 | F181: 58 | G181: =IF(OR(D181="",E181=""),"",D181*E181) -> 1682 | H181: =IF(OR(D181="",F181=""),"",D181*F181) -> 1682 | I181: =IF(OR(G181="",H181=""),"",G181-H181) -> 0 | J181: =IF(OR(B181="",C181=""),"",B181&"|"&C181) -> Egg Shop|Medium | K181: =IF(A181<>"","Cash","") -> Cash
A182: 46127 | B182: Egg Shop | C182: Small | D182: 91 | E182: 55 | F182: 55 | G182: =IF(OR(D182="",E182=""),"",D182*E182) -> 5005 | H182: =IF(OR(D182="",F182=""),"",D182*F182) -> 5005 | I182: =IF(OR(G182="",H182=""),"",G182-H182) -> 0 | J182: =IF(OR(B182="",C182=""),"",B182&"|"&C182) -> Egg Shop|Small | K182: =IF(A182<>"","Cash","") -> Cash
A183: 46127 | B183: Egg Shop | C183: Pullet 1 | D183: 1 | E183: 40 | F183: 40 | G183: =IF(OR(D183="",E183=""),"",D183*E183) -> 40 | H183: =IF(OR(D183="",F183=""),"",D183*F183) -> 40 | I183: =IF(OR(G183="",H183=""),"",G183-H183) -> 0 | J183: =IF(OR(B183="",C183=""),"",B183&"|"&C183) -> Egg Shop|Pullet 1 | K183: =IF(A183<>"","Cash","") -> Cash
A184: 46127 | B184: Egg Shop | C184: Pullet 2 | D184: 0 | E184: 35 | F184: 35 | G184: =IF(OR(D184="",E184=""),"",D184*E184) -> 0 | H184: =IF(OR(D184="",F184=""),"",D184*F184) -> 0 | I184: =IF(OR(G184="",H184=""),"",G184-H184) -> 0 | J184: =IF(OR(B184="",C184=""),"",B184&"|"&C184) -> Egg Shop|Pullet 2 | K184: =IF(A184<>"","Cash","") -> Cash
A185: 46127 | B185: Egg Shop | C185: Broken | D185: -3 | E185: 30 | F185: 30 | G185: =IF(OR(D185="",E185=""),"",D185*E185) -> -90 | H185: =IF(OR(D185="",F185=""),"",D185*F185) -> -90 | I185: =IF(OR(G185="",H185=""),"",G185-H185) -> 0 | J185: =IF(OR(B185="",C185=""),"",B185&"|"&C185) -> Egg Shop|Broken | K185: =IF(A185<>"","Cash","") -> Cash
A186: 46128 | B186: Egg Shop | C186: Large | D186: 4 | E186: 60 | F186: 60 | G186: =IF(OR(D186="",E186=""),"",D186*E186) -> 240 | H186: =IF(OR(D186="",F186=""),"",D186*F186) -> 240 | I186: =IF(OR(G186="",H186=""),"",G186-H186) -> 0 | J186: =IF(OR(B186="",C186=""),"",B186&"|"&C186) -> Egg Shop|Large | K186: =IF(A186<>"","Cash","") -> Cash
A187: 46128 | B187: Egg Shop | C187: Medium | D187: 65 | E187: 58 | F187: 58 | G187: =IF(OR(D187="",E187=""),"",D187*E187) -> 3770 | H187: =IF(OR(D187="",F187=""),"",D187*F187) -> 3770 | I187: =IF(OR(G187="",H187=""),"",G187-H187) -> 0 | J187: =IF(OR(B187="",C187=""),"",B187&"|"&C187) -> Egg Shop|Medium | K187: =IF(A187<>"","Cash","") -> Cash
A188: 46128 | B188: Egg Shop | C188: Small | D188: 68 | E188: 55 | F188: 55 | G188: =IF(OR(D188="",E188=""),"",D188*E188) -> 3740 | H188: =IF(OR(D188="",F188=""),"",D188*F188) -> 3740 | I188: =IF(OR(G188="",H188=""),"",G188-H188) -> 0 | J188: =IF(OR(B188="",C188=""),"",B188&"|"&C188) -> Egg Shop|Small | K188: =IF(A188<>"","Cash","") -> Cash
A189: 46128 | B189: Egg Shop | C189: Pullet 1 | D189: 99 | E189: 40 | F189: 40 | G189: =IF(OR(D189="",E189=""),"",D189*E189) -> 3960 | H189: =IF(OR(D189="",F189=""),"",D189*F189) -> 3960 | I189: =IF(OR(G189="",H189=""),"",G189-H189) -> 0 | J189: =IF(OR(B189="",C189=""),"",B189&"|"&C189) -> Egg Shop|Pullet 1 | K189: =IF(A189<>"","Cash","") -> Cash
A190: 46128 | B190: Egg Shop | C190: Pullet 2 | D190: 35 | E190: 35 | F190: 35 | G190: =IF(OR(D190="",E190=""),"",D190*E190) -> 1225 | H190: =IF(OR(D190="",F190=""),"",D190*F190) -> 1225 | I190: =IF(OR(G190="",H190=""),"",G190-H190) -> 0 | J190: =IF(OR(B190="",C190=""),"",B190&"|"&C190) -> Egg Shop|Pullet 2 | K190: =IF(A190<>"","Cash","") -> Cash
A191: 46128 | B191: Egg Shop | C191: Broken | D191: 0 | E191: 30 | F191: 30 | G191: =IF(OR(D191="",E191=""),"",D191*E191) -> 0 | H191: =IF(OR(D191="",F191=""),"",D191*F191) -> 0 | I191: =IF(OR(G191="",H191=""),"",G191-H191) -> 0 | J191: =IF(OR(B191="",C191=""),"",B191&"|"&C191) -> Egg Shop|Broken | K191: =IF(A191<>"","Cash","") -> Cash
... A240: 46146 | B240: Egg Shop | C240: Pullet 2 | D240: 8 | E240: 35 | F240: 35 | G240: =IF(OR(D240="",E240=""),"",D240*E240) -> 280 | H240: =IF(OR(D240="",F240=""),"",D240*F240) -> 280 | I240: =IF(OR(G240="",H240=""),"",G240-H240) -> 0 | J240: =IF(OR(B240="",C240=""),"",B240&"|"&C240) -> Egg Shop|Pullet 2 | K240: =IF(A240<>"","Cash","") -> Cash
A241: 46146 | B241: Akatsi Feed | C241: LM | D241: 17 | E241: 365 | F241: =IF(B241="Egg Shop","",IF(J241="","",IFERROR(LOOKUP(2,1/(Purchases!$H$3:$H$2002=J241),Purchases!$F$3:$F$2002),""))) -> 352 | G241: =IF(OR(D241="",E241=""),"",D241*E241) -> 6205 | H241: =IF(OR(D241="",F241=""),"",D241*F241) -> 5984 | I241: =IF(OR(G241="",H241=""),"",G241-H241) -> 221 | J241: =IF(OR(B241="",C241=""),"",B241&"|"&C241) -> Akatsi Feed|LM | K241: =IF(A241<>"","Cash","") -> Cash
A242: 46146 | B242: Akatsi Feed | C242: GM | D242: 1 | E242: 350 | F242: =IF(B242="Egg Shop","",IF(J242="","",IFERROR(LOOKUP(2,1/(Purchases!$H$3:$H$2002=J242),Purchases!$F$3:$F$2002),""))) -> 340 | G242: =IF(OR(D242="",E242=""),"",D242*E242) -> 350 | H242: =IF(OR(D242="",F242=""),"",D242*F242) -> 340 | I242: =IF(OR(G242="",H242=""),"",G242-H242) -> 10 | J242: =IF(OR(B242="",C242=""),"",B242&"|"&C242) -> Akatsi Feed|GM | K242: =IF(A242<>"","Cash","") -> Cash
A243: 46146 | B243: Abor Feed | C243: LM | D243: 10 | E243: 365 | F243: =IF(B243="Egg Shop","",IF(J243="","",IFERROR(LOOKUP(2,1/(Purchases!$H$3:$H$2002=J243),Purchases!$F$3:$F$2002),""))) -> 352 | G243: =IF(OR(D243="",E243=""),"",D243*E243) -> 3650 | H243: =IF(OR(D243="",F243=""),"",D243*F243) -> 3520 | I243: =IF(OR(G243="",H243=""),"",G243-H243) -> 130 | J243: =IF(OR(B243="",C243=""),"",B243&"|"&C243) -> Abor Feed|LM | K243: =IF(A243<>"","Cash","") -> Cash
A244: 46146 | B244: Abor Feed | C244: Crates | D244: 2 | E244: 90 | F244: =IF(B244="Egg Shop","",IF(J244="","",IFERROR(LOOKUP(2,1/(Purchases!$H$3:$H$2002=J244),Purchases!$F$3:$F$2002),""))) -> 80 | G244: =IF(OR(D244="",E244=""),"",D244*E244) -> 180 | H244: =IF(OR(D244="",F244=""),"",D244*F244) -> 160 | I244: =IF(OR(G244="",H244=""),"",G244-H244) -> 20 | J244: =IF(OR(B244="",C244=""),"",B244&"|"&C244) -> Abor Feed|Crates | K244: =IF(A244<>"","Cash","") -> Cash
F245: =IF(B245="Egg Shop","",IF(J245="","",IFERROR(LOOKUP(2,1/(Purchases!$H$3:$H$2002=J245),Purchases!$F$3:$F$2002),""))) | G245: =IF(OR(D245="",E245=""),"",D245*E245) | H245: =IF(OR(D245="",F245=""),"",D245*F245) | I245: =IF(OR(G245="",H245=""),"",G245-H245) | J245: =IF(OR(B245="",C245=""),"",B245&"|"&C245) | K245: =IF(A245<>"","Cash","")
F246: =IF(B246="Egg Shop","",IF(J246="","",IFERROR(LOOKUP(2,1/(Purchases!$H$3:$H$2002=J246),Purchases!$F$3:$F$2002),""))) | G246: =IF(OR(D246="",E246=""),"",D246*E246) | H246: =IF(OR(D246="",F246=""),"",D246*F246) | I246: =IF(OR(G246="",H246=""),"",G246-H246) | J246: =IF(OR(B246="",C246=""),"",B246&"|"&C246) | K246: =IF(A246<>"","Cash","")
...

Sheet Stock Summary
A1: TRADING SHOPS STOCK | H1: EGG SHOP STOCK
A2: Shop | B2: Product | C2: Key | D2: Received (Purchases) | E2: Sold | F2: Remaining | H2: Product | I2: Received from Farm | J2: Sold by Egg Shop | K2: Remaining
A3: Akatsi Feed | B3: LM | C3: =IF(OR(A3="",B3=""),"",A3&"|"&B3) -> Akatsi Feed|LM | D3: =IF(C3="","",SUMIFS(Purchases!$E$3:$E$2002,Purchases!$H$3:$H$2002,C3,Purchases!$A$3:$A$2002,">="&'Control Panel'!$B$3,Purchases!$A$3:$A$2002,"<="&'Control Panel'!$C$3)) -> 321 | E3: =IF(C3="","",SUMIFS('Sales Log'!$D$3:$D$2002,'Sales Log'!$J$3:$J$2002,C3,'Sales Log'!$A$3:$A$2002,">="&'Control Panel'!$B$3,'Sales Log'!$A$3:$A$2002,"<="&'Control Panel'!$C$3)) -> 246 | F3: =IF(C3="","",D3-E3) -> 75 | H3: Extra Large | I3: =IF(H3="","",SUMIFS('Egg Transfers'!$C$3:$C$2002,'Egg Transfers'!$B$3:$B$2002,H3,'Egg Transfers'!$A$3:$A$2002,">="&'Control Panel'!$B$3,'Egg Transfers'!$A$3:$A$2002,"<="&'Control Panel'!$C$3)) -> 2 | J3: =IF(H3="","",SUMIFS('Sales Log'!$D$3:$D$2002,'Sales Log'!$B$3:$B$2002,"Egg Shop",'Sales Log'!$C$3:$C$2002,H3,'Sales Log'!$A$3:$A$2002,">="&'Control Panel'!$B$3,'Sales Log'!$A$3:$A$2002,"<="&'Control Panel'!$C$3)) -> 2 | K3: =IF(H3="","",I3-J3) -> 0
A4: Akatsi Feed | B4: GM | C4: =IF(OR(A4="",B4=""),"",A4&"|"&B4) -> Akatsi Feed|GM | D4: =IF(C4="","",SUMIFS(Purchases!$E$3:$E$2002,Purchases!$H$3:$H$2002,C4,Purchases!$A$3:$A$2002,">="&'Control Panel'!$B$3,Purchases!$A$3:$A$2002,"<="&'Control Panel'!$C$3)) -> 58 | E4: =IF(C4="","",SUMIFS('Sales Log'!$D$3:$D$2002,'Sales Log'!$J$3:$J$2002,C4,'Sales Log'!$A$3:$A$2002,">="&'Control Panel'!$B$3,'Sales Log'!$A$3:$A$2002,"<="&'Control Panel'!$C$3)) -> 48 | F4: =IF(C4="","",D4-E4) -> 10 | H4: Large | I4: =IF(H4="","",SUMIFS('Egg Transfers'!$C$3:$C$2002,'Egg Transfers'!$B$3:$B$2002,H4,'Egg Transfers'!$A$3:$A$2002,">="&'Control Panel'!$B$3,'Egg Transfers'!$A$3:$A$2002,"<="&'Control Panel'!$C$3)) -> 84 | J4: =IF(H4="","",SUMIFS('Sales Log'!$D$3:$D$2002,'Sales Log'!$B$3:$B$2002,"Egg Shop",'Sales Log'!$C$3:$C$2002,H4,'Sales Log'!$A$3:$A$2002,">="&'Control Panel'!$B$3,'Sales Log'!$A$3:$A$2002,"<="&'Control Panel'!$C$3)) -> 79 | K4: =IF(H4="","",I4-J4) -> 5
A5: Akatsi Feed | B5: CM | C5: =IF(OR(A5="",B5=""),"",A5&"|"&B5) -> Akatsi Feed|CM | D5: =IF(C5="","",SUMIFS(Purchases!$E$3:$E$2002,Purchases!$H$3:$H$2002,C5,Purchases!$A$3:$A$2002,">="&'Control Panel'!$B$3,Purchases!$A$3:$A$2002,"<="&'Control Panel'!$C$3)) -> 23 | E5: =IF(C5="","",SUMIFS('Sales Log'!$D$3:$D$2002,'Sales Log'!$J$3:$J$2002,C5,'Sales Log'!$A$3:$A$2002,">="&'Control Panel'!$B$3,'Sales Log'!$A$3:$A$2002,"<="&'Control Panel'!$C$3)) -> 17 | F5: =IF(C5="","",D5-E5) -> 6 | H5: Medium | I5: =IF(H5="","",SUMIFS('Egg Transfers'!$C$3:$C$2002,'Egg Transfers'!$B$3:$B$2002,H5,'Egg Transfers'!$A$3:$A$2002,">="&'Control Panel'!$B$3,'Egg Transfers'!$A$3:$A$2002,"<="&'Control Panel'!$C$3)) -> 424 | J5: =IF(H5="","",SUMIFS('Sales Log'!$D$3:$D$2002,'Sales Log'!$B$3:$B$2002,"Egg Shop",'Sales Log'!$C$3:$C$2002,H5,'Sales Log'!$A$3:$A$2002,">="&'Control Panel'!$B$3,'Sales Log'!$A$3:$A$2002,"<="&'Control Panel'!$C$3)) -> 401 | K5: =IF(H5="","",I5-J5) -> 23
A6: Akatsi Feed | B6: BS | C6: =IF(OR(A6="",B6=""),"",A6&"|"&B6) -> Akatsi Feed|BS | D6: =IF(C6="","",SUMIFS(Purchases!$E$3:$E$2002,Purchases!$H$3:$H$2002,C6,Purchases!$A$3:$A$2002,">="&'Control Panel'!$B$3,Purchases!$A$3:$A$2002,"<="&'Control Panel'!$C$3)) -> 0 | E6: =IF(C6="","",SUMIFS('Sales Log'!$D$3:$D$2002,'Sales Log'!$J$3:$J$2002,C6,'Sales Log'!$A$3:$A$2002,">="&'Control Panel'!$B$3,'Sales Log'!$A$3:$A$2002,"<="&'Control Panel'!$C$3)) -> 0 | F6: =IF(C6="","",D6-E6) -> 0 | H6: Small | I6: =IF(H6="","",SUMIFS('Egg Transfers'!$C$3:$C$2002,'Egg Transfers'!$B$3:$B$2002,H6,'Egg Transfers'!$A$3:$A$2002,">="&'Control Panel'!$B$3,'Egg Transfers'!$A$3:$A$2002,"<="&'Control Panel'!$C$3)) -> 958 | J6: =IF(H6="","",SUMIFS('Sales Log'!$D$3:$D$2002,'Sales Log'!$B$3:$B$2002,"Egg Shop",'Sales Log'!$C$3:$C$2002,H6,'Sales Log'!$A$3:$A$2002,">="&'Control Panel'!$B$3,'Sales Log'!$A$3:$A$2002,"<="&'Control Panel'!$C$3)) -> 930.5 | K6: =IF(H6="","",I6-J6) -> 27.5
A7: Akatsi Feed | B7: Hend 5% | C7: =IF(OR(A7="",B7=""),"",A7&"|"&B7) -> Akatsi Feed|Hend 5% | D7: =IF(C7="","",SUMIFS(Purchases!$E$3:$E$2002,Purchases!$H$3:$H$2002,C7,Purchases!$A$3:$A$2002,">="&'Control Panel'!$B$3,Purchases!$A$3:$A$2002,"<="&'Control Panel'!$C$3)) -> 0 | E7: =IF(C7="","",SUMIFS('Sales Log'!$D$3:$D$2002,'Sales Log'!$J$3:$J$2002,C7,'Sales Log'!$A$3:$A$2002,">="&'Control Panel'!$B$3,'Sales Log'!$A$3:$A$2002,"<="&'Control Panel'!$C$3)) -> 0 | F7: =IF(C7="","",D7-E7) -> 0 | H7: Pullet 1 | I7: =IF(H7="","",SUMIFS('Egg Transfers'!$C$3:$C$2002,'Egg Transfers'!$B$3:$B$2002,H7,'Egg Transfers'!$A$3:$A$2002,">="&'Control Panel'!$B$3,'Egg Transfers'!$A$3:$A$2002,"<="&'Control Panel'!$C$3)) -> 1099 | J7: =IF(H7="","",SUMIFS('Sales Log'!$D$3:$D$2002,'Sales Log'!$B$3:$B$2002,"Egg Shop",'Sales Log'!$C$3:$C$2002,H7,'Sales Log'!$A$3:$A$2002,">="&'Control Panel'!$B$3,'Sales Log'!$A$3:$A$2002,"<="&'Control Panel'!$C$3)) -> 1099 | K7: =IF(H7="","",I7-J7) -> 0
A8: Akatsi Feed | B8: GMG | C8: =IF(OR(A8="",B8=""),"",A8&"|"&B8) -> Akatsi Feed|GMG | D8: =IF(C8="","",SUMIFS(Purchases!$E$3:$E$2002,Purchases!$H$3:$H$2002,C8,Purchases!$A$3:$A$2002,">="&'Control Panel'!$B$3,Purchases!$A$3:$A$2002,"<="&'Control Panel'!$C$3)) -> 0 | E8: =IF(C8="","",SUMIFS('Sales Log'!$D$3:$D$2002,'Sales Log'!$J$3:$J$2002,C8,'Sales Log'!$A$3:$A$2002,">="&'Control Panel'!$B$3,'Sales Log'!$A$3:$A$2002,"<="&'Control Panel'!$C$3)) -> 0 | F8: =IF(C8="","",D8-E8) -> 0 | H8: Pullet 2 | I8: =IF(H8="","",SUMIFS('Egg Transfers'!$C$3:$C$2002,'Egg Transfers'!$B$3:$B$2002,H8,'Egg Transfers'!$A$3:$A$2002,">="&'Control Panel'!$B$3,'Egg Transfers'!$A$3:$A$2002,"<="&'Control Panel'!$C$3)) -> 251 | J8: =IF(H8="","",SUMIFS('Sales Log'!$D$3:$D$2002,'Sales Log'!$B$3:$B$2002,"Egg Shop",'Sales Log'!$C$3:$C$2002,H8,'Sales Log'!$A$3:$A$2002,">="&'Control Panel'!$B$3,'Sales Log'!$A$3:$A$2002,"<="&'Control Panel'!$C$3)) -> 251 | K8: =IF(H8="","",I8-J8) -> 0
A9: Akatsi Feed | B9: Crates | C9: =IF(OR(A9="",B9=""),"",A9&"|"&B9) -> Akatsi Feed|Crates | D9: =IF(C9="","",SUMIFS(Purchases!$E$3:$E$2002,Purchases!$H$3:$H$2002,C9,Purchases!$A$3:$A$2002,">="&'Control Panel'!$B$3,Purchases!$A$3:$A$2002,"<="&'Control Panel'!$C$3)) -> 84 | E9: =IF(C9="","",SUMIFS('Sales Log'!$D$3:$D$2002,'Sales Log'!$J$3:$J$2002,C9,'Sales Log'!$A$3:$A$2002,">="&'Control Panel'!$B$3,'Sales Log'!$A$3:$A$2002,"<="&'Control Panel'!$C$3)) -> 48 | F9: =IF(C9="","",D9-E9) -> 36 | H9: Broken | I9: =IF(H9="","",SUMIFS('Egg Transfers'!$C$3:$C$2002,'Egg Transfers'!$B$3:$B$2002,H9,'Egg Transfers'!$A$3:$A$2002,">="&'Control Panel'!$B$3,'Egg Transfers'!$A$3:$A$2002,"<="&'Control Panel'!$C$3)) -> 16.5 | J9: =IF(H9="","",SUMIFS('Sales Log'!$D$3:$D$2002,'Sales Log'!$B$3:$B$2002,"Egg Shop",'Sales Log'!$C$3:$C$2002,H9,'Sales Log'!$A$3:$A$2002,">="&'Control Panel'!$B$3,'Sales Log'!$A$3:$A$2002,"<="&'Control Panel'!$C$3)) -> 16.5 | K9: =IF(H9="","",I9-J9) -> 0
A10: Akatsi Feed | B10: Extra Large | C10: =IF(OR(A10="",B10=""),"",A10&"|"&B10) -> Akatsi Feed|Extra Large | D10: =IF(C10="","",SUMIFS(Purchases!$E$3:$E$2002,Purchases!$H$3:$H$2002,C10,Purchases!$A$3:$A$2002,">="&'Control Panel'!$B$3,Purchases!$A$3:$A$2002,"<="&'Control Panel'!$C$3)) -> 0 | E10: =IF(C10="","",SUMIFS('Sales Log'!$D$3:$D$2002,'Sales Log'!$J$3:$J$2002,C10,'Sales Log'!$A$3:$A$2002,">="&'Control Panel'!$B$3,'Sales Log'!$A$3:$A$2002,"<="&'Control Panel'!$C$3)) -> 0 | F10: =IF(C10="","",D10-E10) -> 0
A11: Akatsi Feed | B11: Large | C11: =IF(OR(A11="",B11=""),"",A11&"|"&B11) -> Akatsi Feed|Large | D11: =IF(C11="","",SUMIFS(Purchases!$E$3:$E$2002,Purchases!$H$3:$H$2002,C11,Purchases!$A$3:$A$2002,">="&'Control Panel'!$B$3,Purchases!$A$3:$A$2002,"<="&'Control Panel'!$C$3)) -> 0 | E11: =IF(C11="","",SUMIFS('Sales Log'!$D$3:$D$2002,'Sales Log'!$J$3:$J$2002,C11,'Sales Log'!$A$3:$A$2002,">="&'Control Panel'!$B$3,'Sales Log'!$A$3:$A$2002,"<="&'Control Panel'!$C$3)) -> 0 | F11: =IF(C11="","",D11-E11) -> 0
A12: Akatsi Feed | B12: Medium | C12: =IF(OR(A12="",B12=""),"",A12&"|"&B12) -> Akatsi Feed|Medium | D12: =IF(C12="","",SUMIFS(Purchases!$E$3:$E$2002,Purchases!$H$3:$H$2002,C12,Purchases!$A$3:$A$2002,">="&'Control Panel'!$B$3,Purchases!$A$3:$A$2002,"<="&'Control Panel'!$C$3)) -> 0 | E12: =IF(C12="","",SUMIFS('Sales Log'!$D$3:$D$2002,'Sales Log'!$J$3:$J$2002,C12,'Sales Log'!$A$3:$A$2002,">="&'Control Panel'!$B$3,'Sales Log'!$A$3:$A$2002,"<="&'Control Panel'!$C$3)) -> 0 | F12: =IF(C12="","",D12-E12) -> 0
A13: Akatsi Feed | B13: Small | C13: =IF(OR(A13="",B13=""),"",A13&"|"&B13) -> Akatsi Feed|Small | D13: =IF(C13="","",SUMIFS(Purchases!$E$3:$E$2002,Purchases!$H$3:$H$2002,C13,Purchases!$A$3:$A$2002,">="&'Control Panel'!$B$3,Purchases!$A$3:$A$2002,"<="&'Control Panel'!$C$3)) -> 0 | E13: =IF(C13="","",SUMIFS('Sales Log'!$D$3:$D$2002,'Sales Log'!$J$3:$J$2002,C13,'Sales Log'!$A$3:$A$2002,">="&'Control Panel'!$B$3,'Sales Log'!$A$3:$A$2002,"<="&'Control Panel'!$C$3)) -> 0 | F13: =IF(C13="","",D13-E13) -> 0
A14: Akatsi Feed | B14: Pullet 1 | C14: =IF(OR(A14="",B14=""),"",A14&"|"&B14) -> Akatsi Feed|Pullet 1 | D14: =IF(C14="","",SUMIFS(Purchases!$E$3:$E$2002,Purchases!$H$3:$H$2002,C14,Purchases!$A$3:$A$2002,">="&'Control Panel'!$B$3,Purchases!$A$3:$A$2002,"<="&'Control Panel'!$C$3)) -> 0 | E14: =IF(C14="","",SUMIFS('Sales Log'!$D$3:$D$2002,'Sales Log'!$J$3:$J$2002,C14,'Sales Log'!$A$3:$A$2002,">="&'Control Panel'!$B$3,'Sales Log'!$A$3:$A$2002,"<="&'Control Panel'!$C$3)) -> 0 | F14: =IF(C14="","",D14-E14) -> 0
A15: Akatsi Feed | B15: Pullet 2 | C15: =IF(OR(A15="",B15=""),"",A15&"|"&B15) -> Akatsi Feed|Pullet 2 | D15: =IF(C15="","",SUMIFS(Purchases!$E$3:$E$2002,Purchases!$H$3:$H$2002,C15,Purchases!$A$3:$A$2002,">="&'Control Panel'!$B$3,Purchases!$A$3:$A$2002,"<="&'Control Panel'!$C$3)) -> 0 | E15: =IF(C15="","",SUMIFS('Sales Log'!$D$3:$D$2002,'Sales Log'!$J$3:$J$2002,C15,'Sales Log'!$A$3:$A$2002,">="&'Control Panel'!$B$3,'Sales Log'!$A$3:$A$2002,"<="&'Control Panel'!$C$3)) -> 0 | F15: =IF(C15="","",D15-E15) -> 0
A16: Akatsi Feed | B16: Broken | C16: =IF(OR(A16="",B16=""),"",A16&"|"&B16) -> Akatsi Feed|Broken | D16: =IF(C16="","",SUMIFS(Purchases!$E$3:$E$2002,Purchases!$H$3:$H$2002,C16,Purchases!$A$3:$A$2002,">="&'Control Panel'!$B$3,Purchases!$A$3:$A$2002,"<="&'Control Panel'!$C$3)) -> 0 | E16: =IF(C16="","",SUMIFS('Sales Log'!$D$3:$D$2002,'Sales Log'!$J$3:$J$2002,C16,'Sales Log'!$A$3:$A$2002,">="&'Control Panel'!$B$3,'Sales Log'!$A$3:$A$2002,"<="&'Control Panel'!$C$3)) -> 0 | F16: =IF(C16="","",D16-E16) -> 0
A17: Abor Feed | B17: LM | C17: =IF(OR(A17="",B17=""),"",A17&"|"&B17) -> Abor Feed|LM | D17: =IF(C17="","",SUMIFS(Purchases!$E$3:$E$2002,Purchases!$H$3:$H$2002,C17,Purchases!$A$3:$A$2002,">="&'Control Panel'!$B$3,Purchases!$A$3:$A$2002,"<="&'Control Panel'!$C$3)) -> 133 | E17: =IF(C17="","",SUMIFS('Sales Log'!$D$3:$D$2002,'Sales Log'!$J$3:$J$2002,C17,'Sales Log'!$A$3:$A$2002,">="&'Control Panel'!$B$3,'Sales Log'!$A$3:$A$2002,"<="&'Control Panel'!$C$3)) -> 98 | F17: =IF(C17="","",D17-E17) -> 35
A18: Abor Feed | B18: GM | C18: =IF(OR(A18="",B18=""),"",A18&"|"&B18) -> Abor Feed|GM | D18: =IF(C18="","",SUMIFS(Purchases!$E$3:$E$2002,Purchases!$H$3:$H$2002,C18,Purchases!$A$3:$A$2002,">="&'Control Panel'!$B$3,Purchases!$A$3:$A$2002,"<="&'Control Panel'!$C$3)) -> 21 | E18: =IF(C18="","",SUMIFS('Sales Log'!$D$3:$D$2002,'Sales Log'!$J$3:$J$2002,C18,'Sales Log'!$A$3:$A$2002,">="&'Control Panel'!$B$3,'Sales Log'!$A$3:$A$2002,"<="&'Control Panel'!$C$3)) -> 11 | F18: =IF(C18="","",D18-E18) -> 10
A19: Abor Feed | B19: CM | C19: =IF(OR(A19="",B19=""),"",A19&"|"&B19) -> Abor Feed|CM | D19: =IF(C19="","",SUMIFS(Purchases!$E$3:$E$2002,Purchases!$H$3:$H$2002,C19,Purchases!$A$3:$A$2002,">="&'Control Panel'!$B$3,Purchases!$A$3:$A$2002,"<="&'Control Panel'!$C$3)) -> 0 | E19: =IF(C19="","",SUMIFS('Sales Log'!$D$3:$D$2002,'Sales Log'!$J$3:$J$2002,C19,'Sales Log'!$A$3:$A$2002,">="&'Control Panel'!$B$3,'Sales Log'!$A$3:$A$2002,"<="&'Control Panel'!$C$3)) -> 0 | F19: =IF(C19="","",D19-E19) -> 0
A20: Abor Feed | B20: BS | C20: =IF(OR(A20="",B20=""),"",A20&"|"&B20) -> Abor Feed|BS | D20: =IF(C20="","",SUMIFS(Purchases!$E$3:$E$2002,Purchases!$H$3:$H$2002,C20,Purchases!$A$3:$A$2002,">="&'Control Panel'!$B$3,Purchases!$A$3:$A$2002,"<="&'Control Panel'!$C$3)) -> 0 | E20: =IF(C20="","",SUMIFS('Sales Log'!$D$3:$D$2002,'Sales Log'!$J$3:$J$2002,C20,'Sales Log'!$A$3:$A$2002,">="&'Control Panel'!$B$3,'Sales Log'!$A$3:$A$2002,"<="&'Control Panel'!$C$3)) -> 0 | F20: =IF(C20="","",D20-E20) -> 0
A21: Abor Feed | B21: Hend 5% | C21: =IF(OR(A21="",B21=""),"",A21&"|"&B21) -> Abor Feed|Hend 5% | D21: =IF(C21="","",SUMIFS(Purchases!$E$3:$E$2002,Purchases!$H$3:$H$2002,C21,Purchases!$A$3:$A$2002,">="&'Control Panel'!$B$3,Purchases!$A$3:$A$2002,"<="&'Control Panel'!$C$3)) -> 0 | E21: =IF(C21="","",SUMIFS('Sales Log'!$D$3:$D$2002,'Sales Log'!$J$3:$J$2002,C21,'Sales Log'!$A$3:$A$2002,">="&'Control Panel'!$B$3,'Sales Log'!$A$3:$A$2002,"<="&'Control Panel'!$C$3)) -> 0 | F21: =IF(C21="","",D21-E21) -> 0
... A37: Mobile Shop | B37: Crates | C37: =IF(OR(A37="",B37=""),"",A37&"|"&B37) -> Mobile Shop|Crates | D37: =IF(C37="","",SUMIFS(Purchases!$E$3:$E$2002,Purchases!$H$3:$H$2002,C37,Purchases!$A$3:$A$2002,">="&'Control Panel'!$B$3,Purchases!$A$3:$A$2002,"<="&'Control Panel'!$C$3)) -> 0 | E37: =IF(C37="","",SUMIFS('Sales Log'!$D$3:$D$2002,'Sales Log'!$J$3:$J$2002,C37,'Sales Log'!$A$3:$A$2002,">="&'Control Panel'!$B$3,'Sales Log'!$A$3:$A$2002,"<="&'Control Panel'!$C$3)) -> 0 | F37: =IF(C37="","",D37-E37) -> 0

Sheet Farm Costs
A1: FARM COSTS LOG
A2: Date | B2: Cost Item | C2: Category | D2: Amount (GHS) | E2: Notes
A3: 46113 | B3: Maize | C3: Feed | D3: 2940
A4: 46113 | B4: Soya | C4: Feed | D4: 1400
A5: 46113 | B5: Concentrate | C5: Feed | D5: 730
A6: 46113 | B6: GMG | C6: Feed | D6: 200
A7: 46113 | B7: Shell | C7: Feed | D7: 200
A8: 46113 | B8: Grinding | C8: Feed | D8: 210
A9: 46113 | B9: Transport | C9: Other | D9: 150
A10: 46115 | B10: Maize | C10: Feed | D10: 7520
A11: 46115 | B11: Soya | C11: Feed | D11: 3850
A12: 46115 | B12: Concentrate | C12: Feed | D12: 2190
A13: 46115 | B13: GMG | C13: Feed | D13: 600
A14: 46115 | B14: Shell | C14: Feed | D14: 600
... A22: 46123 | B22: Soya | C22: Feed | D22: 700
A23: 46123 | B23: Concentrate | C23: Feed
A24: 46123 | B24: GMG | C24: Feed | D24: 100
A25: 46123 | B25: Shell | C25: Feed | D25: 100
A26: 46123 | B26: Grinding | C26: Feed | D26: 100
A27: 46123 | B27: Transport | C27: Other | D27: 100

Sheet Egg Transfers
A1: EGG TRANSFERS – FARM TO EGG SHOP
A2: Date | B2: Product | C2: Qty Sent to Egg Shop | D2: Notes
A3: 46115 | B3: Large | C3: 13
A4: 46115 | B4: Medium | C4: 55
A5: 46115 | B5: Small | C5: 105
A6: 46115 | B6: Pullet 1 | C6: 126
A7: 46115 | B7: Pullet 2 | C7: 45
A8: 46115 | B8: Broken | C8: 0
A9: 46118 | B9: Large | C9: 10
A10: 46118 | B10: Medium | C10: 40
A11: 46118 | B11: Small | C11: 80
A12: 46118 | B12: Pullet 1 | C12: 80
A13: 46118 | B13: Pullet 2 | C13: 30
A14: 46118 | B14: Broken | C14: 0
... A75: 46144 | B75: Broken | C75: 0

Sheet Shop Expenses
A1: SHOP EXPENSES LOG
A2: Date | B2: Shop | C2: Expense Type | D2: Amount (GHS)
A3: 46142 | B3: Akatsi Feed | C3: Rent | D3: 300
A4: 46142 | B4: Abor Feed | C4: Rent | D4: 150
A5: 46142 | B5: Egg Shop | C5: Rent | D5: 190
A6: 46142 | B6: Akatsi Feed | C6: Salary | D6: 1200
A7: 46142 | B7: Abor Feed | C7: Salary | D7: 800
A8: 46142 | B8: Egg Shop | C8: Salary | D8: 1100

Sheet Payroll
A1: PAYROLL – STAFF WAGES
A2: STAFF REGISTER
A3: Staff Name | B3: Role | C3: Location | D3: Monthly Salary (GHS) | E3: Payment Date | F3: Payment Method | G3: Notes
A4: Elinam | B4: Shop Staff | C4: Akatsi Feed | D4: 1200 | E4: 46142 | F4: Cash
A5: Bless | B5: Shop Staff | C5: Abor Feed | D5: 800 | E5: 46143 | F5: Cash
A6: Dela | B6: Shop Staff | C6: Egg Shop | D6: 1100 | E6: 46144 | F6: Cash
A7: Mawufemor | B7: Accounts | C7: Adidome Farm | D7: 1500 | E7: 46145 | F7: Cash
A8: Gifty | B8: Farm Labour | C8: Adidome Farm | D8: 1000 | E8: 46146 | F8: Cash
A9: Lucky | B9: Farm Labour | C9: Akuave Farm | D9: 1600 | E9: 46147 | F9: Cash
A10: Wise | B10: Farm Labour | C10: Akuave Farm | D10: 1250 | E10: 46148 | F10: Cash
A11: Elikplim | B11: Farm Labour | C11: Akuave Farm | D11: 1100 | E11: 46149 | F11: Cash
A12: Gameli | B12: Farm Labour | C12: Akuave Farm | D12: 1100 | E12: 46150 | F12: Cash
A13: Kwaku | B13: Farm Labour | C13: Akuave Farm | D13: 1100 | E13: 46151 | F13: Cash
B14: Farm Labour | C14: Akuave Farm | D14: 0 | F14: Cash | G14: Enter farm wages here
A17: MONTHLY PAYROLL SUMMARY
A18: Total Monthly Wages (GHS) | D18: =SUM(D4:D14) -> 11750
A19: Annual Wages Estimate (GHS) | D19: =D18*12 -> 141000
A21: Wages Paid This Period (from Shop Expenses) | D21: =SUMIFS('Shop Expenses'!$D$3:$D$2002,'Shop Expenses'!$C$3:$C$2002,"Salary",'Shop Expenses'!$A$3:$A$2002,">="&'Control Panel'!$B$3,'Shop Expenses'!$A$3:$A$2002,"<="&'Control Panel'!$C$3) -> 3100

Sheet Cash & Bank
A1: CASH & BANK LEDGER
A2: RULE: All cash sales are automatically banked on the day of sale.
A3: Opening Bank Balance (GHS) | B3: ='Control Panel'!B7 -> 1000
A4: Date | B4: Description | C4: Category | D4: Money In – Sales (Auto) | E4: Money Out – Expenses (Auto) | F4: Running Balance (GHS) | G4: Notes
A5: 46113 | C5: =IF(A5="","","Daily Sales") -> Daily Sales | D5: =IF(A5="","",SUMIFS('Sales Log'!$G$3:$G$2002,'Sales Log'!$A$3:$A$2002,A5)) -> 1895 | E5: =IF(A5="","",SUMIFS('Shop Expenses'!$D$3:$D$2002,'Shop Expenses'!$A$3:$A$2002,A5)+SUMIFS('Farm Costs'!$D$3:$D$2002,'Farm Costs'!$A$3:$A$2002,A5)) -> 5830 | F5: =IF(A5="","",'Control Panel'!B7+D5-E5) -> -2935
A6: 46114 | C6: =IF(A6="","","Daily Sales") -> Daily Sales | D6: =IF(A6="","",SUMIFS('Sales Log'!$G$3:$G$2002,'Sales Log'!$A$3:$A$2002,A6)) -> 2085 | E6: =IF(A6="","",SUMIFS('Shop Expenses'!$D$3:$D$2002,'Shop Expenses'!$A$3:$A$2002,A6)+SUMIFS('Farm Costs'!$D$3:$D$2002,'Farm Costs'!$A$3:$A$2002,A6)) -> 0 | F6: =IF(A6="","",F5+D6-E6) -> -850
A7: 46115 | C7: =IF(A7="","","Daily Sales") -> Daily Sales | D7: =IF(A7="","",SUMIFS('Sales Log'!$G$3:$G$2002,'Sales Log'!$A$3:$A$2002,A7)) -> 20515 | E7: =IF(A7="","",SUMIFS('Shop Expenses'!$D$3:$D$2002,'Shop Expenses'!$A$3:$A$2002,A7)+SUMIFS('Farm Costs'!$D$3:$D$2002,'Farm Costs'!$A$3:$A$2002,A7)) -> 16610 | F7: =IF(A7="","",F6+D7-E7) -> 3055
A8: 46116 | C8: =IF(A8="","","Daily Sales") -> Daily Sales | D8: =IF(A8="","",SUMIFS('Sales Log'!$G$3:$G$2002,'Sales Log'!$A$3:$A$2002,A8)) -> 7760 | E8: =IF(A8="","",SUMIFS('Shop Expenses'!$D$3:$D$2002,'Shop Expenses'!$A$3:$A$2002,A8)+SUMIFS('Farm Costs'!$D$3:$D$2002,'Farm Costs'!$A$3:$A$2002,A8)) -> 0 | F8: =IF(A8="","",F7+D8-E8) -> 10815
A9: 46117 | C9: =IF(A9="","","Daily Sales") -> Daily Sales | D9: =IF(A9="","",SUMIFS('Sales Log'!$G$3:$G$2002,'Sales Log'!$A$3:$A$2002,A9)) -> 120 | E9: =IF(A9="","",SUMIFS('Shop Expenses'!$D$3:$D$2002,'Shop Expenses'!$A$3:$A$2002,A9)+SUMIFS('Farm Costs'!$D$3:$D$2002,'Farm Costs'!$A$3:$A$2002,A9)) -> 0 | F9: =IF(A9="","",F8+D9-E9) -> 10935
A10: 46118 | C10: =IF(A10="","","Daily Sales") -> Daily Sales | D10: =IF(A10="","",SUMIFS('Sales Log'!$G$3:$G$2002,'Sales Log'!$A$3:$A$2002,A10)) -> 26829 | E10: =IF(A10="","",SUMIFS('Shop Expenses'!$D$3:$D$2002,'Shop Expenses'!$A$3:$A$2002,A10)+SUMIFS('Farm Costs'!$D$3:$D$2002,'Farm Costs'!$A$3:$A$2002,A10)) -> 830 | F10: =IF(A10="","",F9+D10-E10) -> 36934
A11: 46119 | C11: =IF(A11="","","Daily Sales") -> Daily Sales | D11: =IF(A11="","",SUMIFS('Sales Log'!$G$3:$G$2002,'Sales Log'!$A$3:$A$2002,A11)) -> 4945 | E11: =IF(A11="","",SUMIFS('Shop Expenses'!$D$3:$D$2002,'Shop Expenses'!$A$3:$A$2002,A11)+SUMIFS('Farm Costs'!$D$3:$D$2002,'Farm Costs'!$A$3:$A$2002,A11)) -> 0 | F11: =IF(A11="","",F10+D11-E11) -> 41879
A12: 46120 | C12: =IF(A12="","","Daily Sales") -> Daily Sales | D12: =IF(A12="","",SUMIFS('Sales Log'!$G$3:$G$2002,'Sales Log'!$A$3:$A$2002,A12)) -> 31280 | E12: =IF(A12="","",SUMIFS('Shop Expenses'!$D$3:$D$2002,'Shop Expenses'!$A$3:$A$2002,A12)+SUMIFS('Farm Costs'!$D$3:$D$2002,'Farm Costs'!$A$3:$A$2002,A12)) -> 0 | F12: =IF(A12="","",F11+D12-E12) -> 73159
A13: 46121 | C13: =IF(A13="","","Daily Sales") -> Daily Sales | D13: =IF(A13="","",SUMIFS('Sales Log'!$G$3:$G$2002,'Sales Log'!$A$3:$A$2002,A13)) -> 2289 | E13: =IF(A13="","",SUMIFS('Shop Expenses'!$D$3:$D$2002,'Shop Expenses'!$A$3:$A$2002,A13)+SUMIFS('Farm Costs'!$D$3:$D$2002,'Farm Costs'!$A$3:$A$2002,A13)) -> 0 | F13: =IF(A13="","",F12+D13-E13) -> 75448
A14: 46122 | C14: =IF(A14="","","Daily Sales") -> Daily Sales | D14: =IF(A14="","",SUMIFS('Sales Log'!$G$3:$G$2002,'Sales Log'!$A$3:$A$2002,A14)) -> 3984 | E14: =IF(A14="","",SUMIFS('Shop Expenses'!$D$3:$D$2002,'Shop Expenses'!$A$3:$A$2002,A14)+SUMIFS('Farm Costs'!$D$3:$D$2002,'Farm Costs'!$A$3:$A$2002,A14)) -> 150 | F14: =IF(A14="","",F13+D14-E14) -> 79282
A15: 46123 | C15: =IF(A15="","","Daily Sales") -> Daily Sales | D15: =IF(A15="","",SUMIFS('Sales Log'!$G$3:$G$2002,'Sales Log'!$A$3:$A$2002,A15)) -> 3536 | E15: =IF(A15="","",SUMIFS('Shop Expenses'!$D$3:$D$2002,'Shop Expenses'!$A$3:$A$2002,A15)+SUMIFS('Farm Costs'!$D$3:$D$2002,'Farm Costs'!$A$3:$A$2002,A15)) -> 3795 | F15: =IF(A15="","",F14+D15-E15) -> 79023
A16: 46124 | C16: =IF(A16="","","Daily Sales") -> Daily Sales | D16: =IF(A16="","",SUMIFS('Sales Log'!$G$3:$G$2002,'Sales Log'!$A$3:$A$2002,A16)) -> 11375.5 | E16: =IF(A16="","",SUMIFS('Shop Expenses'!$D$3:$D$2002,'Shop Expenses'!$A$3:$A$2002,A16)+SUMIFS('Farm Costs'!$D$3:$D$2002,'Farm Costs'!$A$3:$A$2002,A16)) -> 0 | F16: =IF(A16="","",F15+D16-E16) -> 90398.5
A17: 46125 | C17: =IF(A17="","","Daily Sales") -> Daily Sales | D17: =IF(A17="","",SUMIFS('Sales Log'!$G$3:$G$2002,'Sales Log'!$A$3:$A$2002,A17)) -> 5328 | E17: =IF(A17="","",SUMIFS('Shop Expenses'!$D$3:$D$2002,'Shop Expenses'!$A$3:$A$2002,A17)+SUMIFS('Farm Costs'!$D$3:$D$2002,'Farm Costs'!$A$3:$A$2002,A17)) -> 0 | F17: =IF(A17="","",F16+D17-E17) -> 95726.5
... A40: 46148 | C40: =IF(A40="","","Daily Sales") -> Daily Sales | D40: =IF(A40="","",SUMIFS('Sales Log'!$G$3:$G$2002,'Sales Log'!$A$3:$A$2002,A40)) -> 0 | E40: =IF(A40="","",SUMIFS('Shop Expenses'!$D$3:$D$2002,'Shop Expenses'!$A$3:$A$2002,A40)+SUMIFS('Farm Costs'!$D$3:$D$2002,'Farm Costs'!$A$3:$A$2002,A40)) -> 0 | F40: =IF(A40="","",F39+D40-E40) -> 327086.5
C41: =IF(A41="","","Daily Sales") | D41: =IF(A41="","",SUMIFS('Sales Log'!$G$3:$G$2002,'Sales Log'!$A$3:$A$2002,A41)) | E41: =IF(A41="","",SUMIFS('Shop Expenses'!$D$3:$D$2002,'Shop Expenses'!$A$3:$A$2002,A41)+SUMIFS('Farm Costs'!$D$3:$D$2002,'Farm Costs'!$A$3:$A$2002,A41)) | F41: =IF(A41="","",F40+D41-E41)
C42: =IF(A42="","","Daily Sales") | D42: =IF(A42="","",SUMIFS('Sales Log'!$G$3:$G$2002,'Sales Log'!$A$3:$A$2002,A42)) | E42: =IF(A42="","",SUMIFS('Shop Expenses'!$D$3:$D$2002,'Shop Expenses'!$A$3:$A$2002,A42)+SUMIFS('Farm Costs'!$D$3:$D$2002,'Farm Costs'!$A$3:$A$2002,A42)) | F42: =IF(A42="","",F41+D42-E42)
C43: =IF(A43="","","Daily Sales") | D43: =IF(A43="","",SUMIFS('Sales Log'!$G$3:$G$2002,'Sales Log'!$A$3:$A$2002,A43)) | E43: =IF(A43="","",SUMIFS('Shop Expenses'!$D$3:$D$2002,'Shop Expenses'!$A$3:$A$2002,A43)+SUMIFS('Farm Costs'!$D$3:$D$2002,'Farm Costs'!$A$3:$A$2002,A43)) | F43: =IF(A43="","",F42+D43-E43)
C44: =IF(A44="","","Daily Sales") | D44: =IF(A44="","",SUMIFS('Sales Log'!$G$3:$G$2002,'Sales Log'!$A$3:$A$2002,A44)) | E44: =IF(A44="","",SUMIFS('Shop Expenses'!$D$3:$D$2002,'Shop Expenses'!$A$3:$A$2002,A44)+SUMIFS('Farm Costs'!$D$3:$D$2002,'Farm Costs'!$A$3:$A$2002,A44)) | F44: =IF(A44="","",F43+D44-E44)
C45: =IF(A45="","","Daily Sales") | D45: =IF(A45="","",SUMIFS('Sales Log'!$G$3:$G$2002,'Sales Log'!$A$3:$A$2002,A45)) | E45: =IF(A45="","",SUMIFS('Shop Expenses'!$D$3:$D$2002,'Shop Expenses'!$A$3:$A$2002,A45)+SUMIFS('Farm Costs'!$D$3:$D$2002,'Farm Costs'!$A$3:$A$2002,A45)) | F45: =IF(A45="","",F44+D45-E45)
C46: =IF(A46="","","Daily Sales") | D46: =IF(A46="","",SUMIFS('Sales Log'!$G$3:$G$2002,'Sales Log'!$A$3:$A$2002,A46)) | E46: =IF(A46="","",SUMIFS('Shop Expenses'!$D$3:$D$2002,'Shop Expenses'!$A$3:$A$2002,A46)+SUMIFS('Farm Costs'!$D$3:$D$2002,'Farm Costs'!$A$3:$A$2002,A46)) | F46: =IF(A46="","",F45+D46-E46)
C47: =IF(A47="","","Daily Sales") | D47: =IF(A47="","",SUMIFS('Sales Log'!$G$3:$G$2002,'Sales Log'!$A$3:$A$2002,A47)) | E47: =IF(A47="","",SUMIFS('Shop Expenses'!$D$3:$D$2002,'Shop Expenses'!$A$3:$A$2002,A47)+SUMIFS('Farm Costs'!$D$3:$D$2002,'Farm Costs'!$A$3:$A$2002,A47)) | F47: =IF(A47="","",F46+D47-E47)
C48: =IF(A48="","","Daily Sales") | D48: =IF(A48="","",SUMIFS('Sales Log'!$G$3:$G$2002,'Sales Log'!$A$3:$A$2002,A48)) | E48: =IF(A48="","",SUMIFS('Shop Expenses'!$D$3:$D$2002,'Shop Expenses'!$A$3:$A$2002,A48)+SUMIFS('Farm Costs'!$D$3:$D$2002,'Farm Costs'!$A$3:$A$2002,A48)) | F48: =IF(A48="","",F47+D48-E48)
C49: =IF(A49="","","Daily Sales") | D49: =IF(A49="","",SUMIFS('Sales Log'!$G$3:$G$2002,'Sales Log'!$A$3:$A$2002,A49)) | E49: =IF(A49="","",SUMIFS('Shop Expenses'!$D$3:$D$2002,'Shop Expenses'!$A$3:$A$2002,A49)+SUMIFS('Farm Costs'!$D$3:$D$2002,'Farm Costs'!$A$3:$A$2002,A49)) | F49: =IF(A49="","",F48+D49-E49)
C50: =IF(A50="","","Daily Sales") | D50: =IF(A50="","",SUMIFS('Sales Log'!$G$3:$G$2002,'Sales Log'!$A$3:$A$2002,A50)) | E50: =IF(A50="","",SUMIFS('Shop Expenses'!$D$3:$D$2002,'Shop Expenses'!$A$3:$A$2002,A50)+SUMIFS('Farm Costs'!$D$3:$D$2002,'Farm Costs'!$A$3:$A$2002,A50)) | F50: =IF(A50="","",F49+D50-E50)
C51: =IF(A51="","","Daily Sales") | D51: =IF(A51="","",SUMIFS('Sales Log'!$G$3:$G$2002,'Sales Log'!$A$3:$A$2002,A51)) | E51: =IF(A51="","",SUMIFS('Shop Expenses'!$D$3:$D$2002,'Shop Expenses'!$A$3:$A$2002,A51)+SUMIFS('Farm Costs'!$D$3:$D$2002,'Farm Costs'!$A$3:$A$2002,A51)) | F51: =IF(A51="","",F50+D51-E51)
C52: =IF(A52="","","Daily Sales") | D52: =IF(A52="","",SUMIFS('Sales Log'!$G$3:$G$2002,'Sales Log'!$A$3:$A$2002,A52)) | E52: =IF(A52="","",SUMIFS('Shop Expenses'!$D$3:$D$2002,'Shop Expenses'!$A$3:$A$2002,A52)+SUMIFS('Farm Costs'!$D$3:$D$2002,'Farm Costs'!$A$3:$A$2002,A52)) | F52: =IF(A52="","",F51+D52-E52)
... C405: =IF(A405="","","Daily Sales") | D405: =IF(A405="","",SUMIFS('Sales Log'!$G$3:$G$2002,'Sales Log'!$A$3:$A$2002,A405)) | E405: =IF(A405="","",SUMIFS('Shop Expenses'!$D$3:$D$2002,'Shop Expenses'!$A$3:$A$2002,A405)+SUMIFS('Farm Costs'!$D$3:$D$2002,'Farm Costs'!$A$3:$A$2002,A405)) | F405: =IF(A405="","",F404+D405-E405)

Sheet Feed Inventory
A1: FEED INVENTORY TRACKER
A2: Ingredient | B2: Unit | C2: Opening Stock | D2: Purchased (Qty) | E2: Used (Qty) | F2: Closing Stock | G2: Unit Cost (GHS) | H2: Stock Value (GHS)
A3: Maize | B3: Bag (50kg) | C3: 0 | D3: 0 | E3: 0 | F3: =C3+D3-E3 -> 0 | G3: 0 | H3: =F3*G3 -> 0
A4: Soya | B4: Bag (50kg) | C4: 0 | D4: 0 | E4: 0 | F4: =C4+D4-E4 -> 0 | G4: 0 | H4: =F4*G4 -> 0
A5: Concentrate | B5: Bag (25kg) | C5: 0 | D5: 0 | E5: 0 | F5: =C5+D5-E5 -> 0 | G5: 0 | H5: =F5*G5 -> 0
A6: GMG | B6: Bag | C6: 0 | D6: 0 | E6: 0 | F6: =C6+D6-E6 -> 0 | G6: 0 | H6: =F6*G6 -> 0
A7: Shell | B7: Bag | C7: 0 | D7: 0 | E7: 0 | F7: =C7+D7-E7 -> 0 | G7: 0 | H7: =F7*G7 -> 0
G8: TOTAL STOCK VALUE | H8: =SUM(H3:H7) -> 0

Sheet Shop Profitability
A1: SHOP PROFITABILITY
A2: Unit | B2: Sales (GHS) | C2: Cost of Sales (GHS) | D2: Gross Profit (GHS) | E2: Direct Expenses (GHS) | F2: Net Profit (GHS)
A3: Akatsi Feed | B3: =SUMIFS('Sales Log'!$G$3:$G$2002,'Sales Log'!$B$3:$B$2002,A3,'Sales Log'!$A$3:$A$2002,">="&'Control Panel'!$B$3,'Sales Log'!$A$3:$A$2002,"<="&'Control Panel'!$C$3) -> 117200 | C3: =SUMIFS('Sales Log'!$H$3:$H$2002,'Sales Log'!$B$3:$B$2002,A3,'Sales Log'!$A$3:$A$2002,">="&'Control Panel'!$B$3,'Sales Log'!$A$3:$A$2002,"<="&'Control Panel'!$C$3) -> 112821 | D3: =B3-C3 -> 4379 | E3: =SUMIFS('Shop Expenses'!$D$3:$D$2002,'Shop Expenses'!$B$3:$B$2002,A3,'Shop Expenses'!$A$3:$A$2002,">="&'Control Panel'!$B$3,'Shop Expenses'!$A$3:$A$2002,"<="&'Control Panel'!$C$3) -> 1500 | F3: =D3-E3 -> 2879
A4: Abor Feed | B4: =SUMIFS('Sales Log'!$G$3:$G$2002,'Sales Log'!$B$3:$B$2002,A4,'Sales Log'!$A$3:$A$2002,">="&'Control Panel'!$B$3,'Sales Log'!$A$3:$A$2002,"<="&'Control Panel'!$C$3) -> 39840 | C4: =SUMIFS('Sales Log'!$H$3:$H$2002,'Sales Log'!$B$3:$B$2002,A4,'Sales Log'!$A$3:$A$2002,">="&'Control Panel'!$B$3,'Sales Log'!$A$3:$A$2002,"<="&'Control Panel'!$C$3) -> 38396 | D4: =B4-C4 -> 1444 | E4: =SUMIFS('Shop Expenses'!$D$3:$D$2002,'Shop Expenses'!$B$3:$B$2002,A4,'Shop Expenses'!$A$3:$A$2002,">="&'Control Panel'!$B$3,'Shop Expenses'!$A$3:$A$2002,"<="&'Control Panel'!$C$3) -> 950 | F4: =D4-E4 -> 494
A5: Mobile Shop | B5: =SUMIFS('Sales Log'!$G$3:$G$2002,'Sales Log'!$B$3:$B$2002,A5,'Sales Log'!$A$3:$A$2002,">="&'Control Panel'!$B$3,'Sales Log'!$A$3:$A$2002,"<="&'Control Panel'!$C$3) -> 68921 | C5: =SUMIFS('Sales Log'!$H$3:$H$2002,'Sales Log'!$B$3:$B$2002,A5,'Sales Log'!$A$3:$A$2002,">="&'Control Panel'!$B$3,'Sales Log'!$A$3:$A$2002,"<="&'Control Panel'!$C$3) -> 67836 | D5: =B5-C5 -> 1085 | E5: =SUMIFS('Shop Expenses'!$D$3:$D$2002,'Shop Expenses'!$B$3:$B$2002,A5,'Shop Expenses'!$A$3:$A$2002,">="&'Control Panel'!$B$3,'Shop Expenses'!$A$3:$A$2002,"<="&'Control Panel'!$C$3) -> 0 | F5: =D5-E5 -> 1085
A6: Egg Shop | B6: =SUMIFS('Sales Log'!$G$3:$G$2002,'Sales Log'!$B$3:$B$2002,A6,'Sales Log'!$A$3:$A$2002,">="&'Control Panel'!$B$3,'Sales Log'!$A$3:$A$2002,"<="&'Control Panel'!$C$3) -> 131080.5 | C6: =SUMIFS('Sales Log'!$H$3:$H$2002,'Sales Log'!$B$3:$B$2002,A6,'Sales Log'!$A$3:$A$2002,">="&'Control Panel'!$B$3,'Sales Log'!$A$3:$A$2002,"<="&'Control Panel'!$C$3) -> 131080.5 | D6: =B6-C6 -> 0 | E6: =SUMIFS('Shop Expenses'!$D$3:$D$2002,'Shop Expenses'!$B$3:$B$2002,A6,'Shop Expenses'!$A$3:$A$2002,">="&'Control Panel'!$B$3,'Shop Expenses'!$A$3:$A$2002,"<="&'Control Panel'!$C$3) -> 1290 | F6: =D6-E6 -> -1290
A7: TOTAL | B7: =SUM(B3:B6) -> 357041.5 | C7: =SUM(C3:C6) -> 350133.5 | D7: =SUM(D3:D6) -> 6908 | E7: =SUM(E3:E6) -> 3740 | F7: =SUM(F3:F6) -> 3168

Sheet Monthly Summary
A1: MONTHLY SALES SUMMARY
A2: Akatsi Feed
A3: Product | B3: Qty Sold | C3: Total Sales (GHS) | D3: Total Cost (GHS) | E3: Gross Profit (GHS) | F3: Margin %
A4: LM | B4: =SUMPRODUCT(('Sales Log'!$B$3:$B$2002="Akatsi Feed")*('Sales Log'!$C$3:$C$2002="LM")*('Sales Log'!$A$3:$A$2002>='Control Panel'!$B$3)*('Sales Log'!$A$3:$A$2002<='Control Panel'!$C$3)*('Sales Log'!$D$3:$D$2002)) -> 246 | C4: =SUMPRODUCT(('Sales Log'!$B$3:$B$2002="Akatsi Feed")*('Sales Log'!$C$3:$C$2002="LM")*('Sales Log'!$A$3:$A$2002>='Control Panel'!$B$3)*('Sales Log'!$A$3:$A$2002<='Control Panel'!$C$3)*('Sales Log'!$G$3:$G$2002)) -> #VALUE! | D4: =SUMPRODUCT(('Sales Log'!$B$3:$B$2002="Akatsi Feed")*('Sales Log'!$C$3:$C$2002="LM")*('Sales Log'!$A$3:$A$2002>='Control Panel'!$B$3)*('Sales Log'!$A$3:$A$2002<='Control Panel'!$C$3)*('Sales Log'!$H$3:$H$2002)) -> #VALUE! | E4: =C4-D4 -> #VALUE! | F4: =IF(C4>0,E4/C4*100,0) -> #VALUE!
A5: GM | B5: =SUMPRODUCT(('Sales Log'!$B$3:$B$2002="Akatsi Feed")*('Sales Log'!$C$3:$C$2002="GM")*('Sales Log'!$A$3:$A$2002>='Control Panel'!$B$3)*('Sales Log'!$A$3:$A$2002<='Control Panel'!$C$3)*('Sales Log'!$D$3:$D$2002)) -> 48 | C5: =SUMPRODUCT(('Sales Log'!$B$3:$B$2002="Akatsi Feed")*('Sales Log'!$C$3:$C$2002="GM")*('Sales Log'!$A$3:$A$2002>='Control Panel'!$B$3)*('Sales Log'!$A$3:$A$2002<='Control Panel'!$C$3)*('Sales Log'!$G$3:$G$2002)) -> #VALUE! | D5: =SUMPRODUCT(('Sales Log'!$B$3:$B$2002="Akatsi Feed")*('Sales Log'!$C$3:$C$2002="GM")*('Sales Log'!$A$3:$A$2002>='Control Panel'!$B$3)*('Sales Log'!$A$3:$A$2002<='Control Panel'!$C$3)*('Sales Log'!$H$3:$H$2002)) -> #VALUE! | E5: =C5-D5 -> #VALUE! | F5: =IF(C5>0,E5/C5*100,0) -> #VALUE!
A6: CM | B6: =SUMPRODUCT(('Sales Log'!$B$3:$B$2002="Akatsi Feed")*('Sales Log'!$C$3:$C$2002="CM")*('Sales Log'!$A$3:$A$2002>='Control Panel'!$B$3)*('Sales Log'!$A$3:$A$2002<='Control Panel'!$C$3)*('Sales Log'!$D$3:$D$2002)) -> 17 | C6: =SUMPRODUCT(('Sales Log'!$B$3:$B$2002="Akatsi Feed")*('Sales Log'!$C$3:$C$2002="CM")*('Sales Log'!$A$3:$A$2002>='Control Panel'!$B$3)*('Sales Log'!$A$3:$A$2002<='Control Panel'!$C$3)*('Sales Log'!$G$3:$G$2002)) -> #VALUE! | D6: =SUMPRODUCT(('Sales Log'!$B$3:$B$2002="Akatsi Feed")*('Sales Log'!$C$3:$C$2002="CM")*('Sales Log'!$A$3:$A$2002>='Control Panel'!$B$3)*('Sales Log'!$A$3:$A$2002<='Control Panel'!$C$3)*('Sales Log'!$H$3:$H$2002)) -> #VALUE! | E6: =C6-D6 -> #VALUE! | F6: =IF(C6>0,E6/C6*100,0) -> #VALUE!
A7: BS | B7: =SUMPRODUCT(('Sales Log'!$B$3:$B$2002="Akatsi Feed")*('Sales Log'!$C$3:$C$2002="BS")*('Sales Log'!$A$3:$A$2002>='Control Panel'!$B$3)*('Sales Log'!$A$3:$A$2002<='Control Panel'!$C$3)*('Sales Log'!$D$3:$D$2002)) -> 0 | C7: =SUMPRODUCT(('Sales Log'!$B$3:$B$2002="Akatsi Feed")*('Sales Log'!$C$3:$C$2002="BS")*('Sales Log'!$A$3:$A$2002>='Control Panel'!$B$3)*('Sales Log'!$A$3:$A$2002<='Control Panel'!$C$3)*('Sales Log'!$G$3:$G$2002)) -> #VALUE! | D7: =SUMPRODUCT(('Sales Log'!$B$3:$B$2002="Akatsi Feed")*('Sales Log'!$C$3:$C$2002="BS")*('Sales Log'!$A$3:$A$2002>='Control Panel'!$B$3)*('Sales Log'!$A$3:$A$2002<='Control Panel'!$C$3)*('Sales Log'!$H$3:$H$2002)) -> #VALUE! | E7: =C7-D7 -> #VALUE! | F7: =IF(C7>0,E7/C7*100,0) -> #VALUE!
A8: Hend 5% | B8: =SUMPRODUCT(('Sales Log'!$B$3:$B$2002="Akatsi Feed")*('Sales Log'!$C$3:$C$2002="Hend 5%")*('Sales Log'!$A$3:$A$2002>='Control Panel'!$B$3)*('Sales Log'!$A$3:$A$2002<='Control Panel'!$C$3)*('Sales Log'!$D$3:$D$2002)) -> 0 | C8: =SUMPRODUCT(('Sales Log'!$B$3:$B$2002="Akatsi Feed")*('Sales Log'!$C$3:$C$2002="Hend 5%")*('Sales Log'!$A$3:$A$2002>='Control Panel'!$B$3)*('Sales Log'!$A$3:$A$2002<='Control Panel'!$C$3)*('Sales Log'!$G$3:$G$2002)) -> #VALUE! | D8: =SUMPRODUCT(('Sales Log'!$B$3:$B$2002="Akatsi Feed")*('Sales Log'!$C$3:$C$2002="Hend 5%")*('Sales Log'!$A$3:$A$2002>='Control Panel'!$B$3)*('Sales Log'!$A$3:$A$2002<='Control Panel'!$C$3)*('Sales Log'!$H$3:$H$2002)) -> #VALUE! | E8: =C8-D8 -> #VALUE! | F8: =IF(C8>0,E8/C8*100,0) -> #VALUE!
A9: GMG | B9: =SUMPRODUCT(('Sales Log'!$B$3:$B$2002="Akatsi Feed")*('Sales Log'!$C$3:$C$2002="GMG")*('Sales Log'!$A$3:$A$2002>='Control Panel'!$B$3)*('Sales Log'!$A$3:$A$2002<='Control Panel'!$C$3)*('Sales Log'!$D$3:$D$2002)) -> 0 | C9: =SUMPRODUCT(('Sales Log'!$B$3:$B$2002="Akatsi Feed")*('Sales Log'!$C$3:$C$2002="GMG")*('Sales Log'!$A$3:$A$2002>='Control Panel'!$B$3)*('Sales Log'!$A$3:$A$2002<='Control Panel'!$C$3)*('Sales Log'!$G$3:$G$2002)) -> #VALUE! | D9: =SUMPRODUCT(('Sales Log'!$B$3:$B$2002="Akatsi Feed")*('Sales Log'!$C$3:$C$2002="GMG")*('Sales Log'!$A$3:$A$2002>='Control Panel'!$B$3)*('Sales Log'!$A$3:$A$2002<='Control Panel'!$C$3)*('Sales Log'!$H$3:$H$2002)) -> #VALUE! | E9: =C9-D9 -> #VALUE! | F9: =IF(C9>0,E9/C9*100,0) -> #VALUE!
A10: Crates | B10: =SUMPRODUCT(('Sales Log'!$B$3:$B$2002="Akatsi Feed")*('Sales Log'!$C$3:$C$2002="Crates")*('Sales Log'!$A$3:$A$2002>='Control Panel'!$B$3)*('Sales Log'!$A$3:$A$2002<='Control Panel'!$C$3)*('Sales Log'!$D$3:$D$2002)) -> 48 | C10: =SUMPRODUCT(('Sales Log'!$B$3:$B$2002="Akatsi Feed")*('Sales Log'!$C$3:$C$2002="Crates")*('Sales Log'!$A$3:$A$2002>='Control Panel'!$B$3)*('Sales Log'!$A$3:$A$2002<='Control Panel'!$C$3)*('Sales Log'!$G$3:$G$2002)) -> #VALUE! | D10: =SUMPRODUCT(('Sales Log'!$B$3:$B$2002="Akatsi Feed")*('Sales Log'!$C$3:$C$2002="Crates")*('Sales Log'!$A$3:$A$2002>='Control Panel'!$B$3)*('Sales Log'!$A$3:$A$2002<='Control Panel'!$C$3)*('Sales Log'!$H$3:$H$2002)) -> #VALUE! | E10: =C10-D10 -> #VALUE! | F10: =IF(C10>0,E10/C10*100,0) -> #VALUE!
A12: Abor Feed
A13: Product | B13: Qty Sold | C13: Total Sales (GHS) | D13: Total Cost (GHS) | E13: Gross Profit (GHS) | F13: Margin %
A14: LM | B14: =SUMPRODUCT(('Sales Log'!$B$3:$B$2002="Abor Feed")*('Sales Log'!$C$3:$C$2002="LM")*('Sales Log'!$A$3:$A$2002>='Control Panel'!$B$3)*('Sales Log'!$A$3:$A$2002<='Control Panel'!$C$3)*('Sales Log'!$D$3:$D$2002)) -> 98 | C14: =SUMPRODUCT(('Sales Log'!$B$3:$B$2002="Abor Feed")*('Sales Log'!$C$3:$C$2002="LM")*('Sales Log'!$A$3:$A$2002>='Control Panel'!$B$3)*('Sales Log'!$A$3:$A$2002<='Control Panel'!$C$3)*('Sales Log'!$G$3:$G$2002)) -> #VALUE! | D14: =SUMPRODUCT(('Sales Log'!$B$3:$B$2002="Abor Feed")*('Sales Log'!$C$3:$C$2002="LM")*('Sales Log'!$A$3:$A$2002>='Control Panel'!$B$3)*('Sales Log'!$A$3:$A$2002<='Control Panel'!$C$3)*('Sales Log'!$H$3:$H$2002)) -> #VALUE! | E14: =C14-D14 -> #VALUE! | F14: =IF(C14>0,E14/C14*100,0) -> #VALUE!
A15: GM | B15: =SUMPRODUCT(('Sales Log'!$B$3:$B$2002="Abor Feed")*('Sales Log'!$C$3:$C$2002="GM")*('Sales Log'!$A$3:$A$2002>='Control Panel'!$B$3)*('Sales Log'!$A$3:$A$2002<='Control Panel'!$C$3)*('Sales Log'!$D$3:$D$2002)) -> 11 | C15: =SUMPRODUCT(('Sales Log'!$B$3:$B$2002="Abor Feed")*('Sales Log'!$C$3:$C$2002="GM")*('Sales Log'!$A$3:$A$2002>='Control Panel'!$B$3)*('Sales Log'!$A$3:$A$2002<='Control Panel'!$C$3)*('Sales Log'!$G$3:$G$2002)) -> #VALUE! | D15: =SUMPRODUCT(('Sales Log'!$B$3:$B$2002="Abor Feed")*('Sales Log'!$C$3:$C$2002="GM")*('Sales Log'!$A$3:$A$2002>='Control Panel'!$B$3)*('Sales Log'!$A$3:$A$2002<='Control Panel'!$C$3)*('Sales Log'!$H$3:$H$2002)) -> #VALUE! | E15: =C15-D15 -> #VALUE! | F15: =IF(C15>0,E15/C15*100,0) -> #VALUE!
A16: CM | B16: =SUMPRODUCT(('Sales Log'!$B$3:$B$2002="Abor Feed")*('Sales Log'!$C$3:$C$2002="CM")*('Sales Log'!$A$3:$A$2002>='Control Panel'!$B$3)*('Sales Log'!$A$3:$A$2002<='Control Panel'!$C$3)*('Sales Log'!$D$3:$D$2002)) -> 0 | C16: =SUMPRODUCT(('Sales Log'!$B$3:$B$2002="Abor Feed")*('Sales Log'!$C$3:$C$2002="CM")*('Sales Log'!$A$3:$A$2002>='Control Panel'!$B$3)*('Sales Log'!$A$3:$A$2002<='Control Panel'!$C$3)*('Sales Log'!$G$3:$G$2002)) -> #VALUE! | D16: =SUMPRODUCT(('Sales Log'!$B$3:$B$2002="Abor Feed")*('Sales Log'!$C$3:$C$2002="CM")*('Sales Log'!$A$3:$A$2002>='Control Panel'!$B$3)*('Sales Log'!$A$3:$A$2002<='Control Panel'!$C$3)*('Sales Log'!$H$3:$H$2002)) -> #VALUE! | E16: =C16-D16 -> #VALUE! | F16: =IF(C16>0,E16/C16*100,0) -> #VALUE!
A17: BS | B17: =SUMPRODUCT(('Sales Log'!$B$3:$B$2002="Abor Feed")*('Sales Log'!$C$3:$C$2002="BS")*('Sales Log'!$A$3:$A$2002>='Control Panel'!$B$3)*('Sales Log'!$A$3:$A$2002<='Control Panel'!$C$3)*('Sales Log'!$D$3:$D$2002)) -> 0 | C17: =SUMPRODUCT(('Sales Log'!$B$3:$B$2002="Abor Feed")*('Sales Log'!$C$3:$C$2002="BS")*('Sales Log'!$A$3:$A$2002>='Control Panel'!$B$3)*('Sales Log'!$A$3:$A$2002<='Control Panel'!$C$3)*('Sales Log'!$G$3:$G$2002)) -> #VALUE! | D17: =SUMPRODUCT(('Sales Log'!$B$3:$B$2002="Abor Feed")*('Sales Log'!$C$3:$C$2002="BS")*('Sales Log'!$A$3:$A$2002>='Control Panel'!$B$3)*('Sales Log'!$A$3:$A$2002<='Control Panel'!$C$3)*('Sales Log'!$H$3:$H$2002)) -> #VALUE! | E17: =C17-D17 -> #VALUE! | F17: =IF(C17>0,E17/C17*100,0) -> #VALUE!
A18: Hend 5% | B18: =SUMPRODUCT(('Sales Log'!$B$3:$B$2002="Abor Feed")*('Sales Log'!$C$3:$C$2002="Hend 5%")*('Sales Log'!$A$3:$A$2002>='Control Panel'!$B$3)*('Sales Log'!$A$3:$A$2002<='Control Panel'!$C$3)*('Sales Log'!$D$3:$D$2002)) -> 0 | C18: =SUMPRODUCT(('Sales Log'!$B$3:$B$2002="Abor Feed")*('Sales Log'!$C$3:$C$2002="Hend 5%")*('Sales Log'!$A$3:$A$2002>='Control Panel'!$B$3)*('Sales Log'!$A$3:$A$2002<='Control Panel'!$C$3)*('Sales Log'!$G$3:$G$2002)) -> #VALUE! | D18: =SUMPRODUCT(('Sales Log'!$B$3:$B$2002="Abor Feed")*('Sales Log'!$C$3:$C$2002="Hend 5%")*('Sales Log'!$A$3:$A$2002>='Control Panel'!$B$3)*('Sales Log'!$A$3:$A$2002<='Control Panel'!$C$3)*('Sales Log'!$H$3:$H$2002)) -> #VALUE! | E18: =C18-D18 -> #VALUE! | F18: =IF(C18>0,E18/C18*100,0) -> #VALUE!
A19: GMG | B19: =SUMPRODUCT(('Sales Log'!$B$3:$B$2002="Abor Feed")*('Sales Log'!$C$3:$C$2002="GMG")*('Sales Log'!$A$3:$A$2002>='Control Panel'!$B$3)*('Sales Log'!$A$3:$A$2002<='Control Panel'!$C$3)*('Sales Log'!$D$3:$D$2002)) -> 0 | C19: =SUMPRODUCT(('Sales Log'!$B$3:$B$2002="Abor Feed")*('Sales Log'!$C$3:$C$2002="GMG")*('Sales Log'!$A$3:$A$2002>='Control Panel'!$B$3)*('Sales Log'!$A$3:$A$2002<='Control Panel'!$C$3)*('Sales Log'!$G$3:$G$2002)) -> #VALUE! | D19: =SUMPRODUCT(('Sales Log'!$B$3:$B$2002="Abor Feed")*('Sales Log'!$C$3:$C$2002="GMG")*('Sales Log'!$A$3:$A$2002>='Control Panel'!$B$3)*('Sales Log'!$A$3:$A$2002<='Control Panel'!$C$3)*('Sales Log'!$H$3:$H$2002)) -> #VALUE! | E19: =C19-D19 -> #VALUE! | F19: =IF(C19>0,E19/C19*100,0) -> #VALUE!
A20: Crates | B20: =SUMPRODUCT(('Sales Log'!$B$3:$B$2002="Abor Feed")*('Sales Log'!$C$3:$C$2002="Crates")*('Sales Log'!$A$3:$A$2002>='Control Panel'!$B$3)*('Sales Log'!$A$3:$A$2002<='Control Panel'!$C$3)*('Sales Log'!$D$3:$D$2002)) -> 2 | C20: =SUMPRODUCT(('Sales Log'!$B$3:$B$2002="Abor Feed")*('Sales Log'!$C$3:$C$2002="Crates")*('Sales Log'!$A$3:$A$2002>='Control Panel'!$B$3)*('Sales Log'!$A$3:$A$2002<='Control Panel'!$C$3)*('Sales Log'!$G$3:$G$2002)) -> #VALUE! | D20: =SUMPRODUCT(('Sales Log'!$B$3:$B$2002="Abor Feed")*('Sales Log'!$C$3:$C$2002="Crates")*('Sales Log'!$A$3:$A$2002>='Control Panel'!$B$3)*('Sales Log'!$A$3:$A$2002<='Control Panel'!$C$3)*('Sales Log'!$H$3:$H$2002)) -> #VALUE! | E20: =C20-D20 -> #VALUE! | F20: =IF(C20>0,E20/C20*100,0) -> #VALUE!
A22: Mobile Shop
A23: Product | B23: Qty Sold | C23: Total Sales (GHS) | D23: Total Cost (GHS) | E23: Gross Profit (GHS) | F23: Margin %
A24: LM | B24: =SUMPRODUCT(('Sales Log'!$B$3:$B$2002="Mobile Shop")*('Sales Log'!$C$3:$C$2002="LM")*('Sales Log'!$A$3:$A$2002>='Control Panel'!$B$3)*('Sales Log'!$A$3:$A$2002<='Control Panel'!$C$3)*('Sales Log'!$D$3:$D$2002)) -> 143 | C24: =SUMPRODUCT(('Sales Log'!$B$3:$B$2002="Mobile Shop")*('Sales Log'!$C$3:$C$2002="LM")*('Sales Log'!$A$3:$A$2002>='Control Panel'!$B$3)*('Sales Log'!$A$3:$A$2002<='Control Panel'!$C$3)*('Sales Log'!$G$3:$G$2002)) -> #VALUE! | D24: =SUMPRODUCT(('Sales Log'!$B$3:$B$2002="Mobile Shop")*('Sales Log'!$C$3:$C$2002="LM")*('Sales Log'!$A$3:$A$2002>='Control Panel'!$B$3)*('Sales Log'!$A$3:$A$2002<='Control Panel'!$C$3)*('Sales Log'!$H$3:$H$2002)) -> #VALUE! | E24: =C24-D24 -> #VALUE! | F24: =IF(C24>0,E24/C24*100,0) -> #VALUE!
A25: GM | B25: =SUMPRODUCT(('Sales Log'!$B$3:$B$2002="Mobile Shop")*('Sales Log'!$C$3:$C$2002="GM")*('Sales Log'!$A$3:$A$2002>='Control Panel'!$B$3)*('Sales Log'!$A$3:$A$2002<='Control Panel'!$C$3)*('Sales Log'!$D$3:$D$2002)) -> 2 | C25: =SUMPRODUCT(('Sales Log'!$B$3:$B$2002="Mobile Shop")*('Sales Log'!$C$3:$C$2002="GM")*('Sales Log'!$A$3:$A$2002>='Control Panel'!$B$3)*('Sales Log'!$A$3:$A$2002<='Control Panel'!$C$3)*('Sales Log'!$G$3:$G$2002)) -> #VALUE! | D25: =SUMPRODUCT(('Sales Log'!$B$3:$B$2002="Mobile Shop")*('Sales Log'!$C$3:$C$2002="GM")*('Sales Log'!$A$3:$A$2002>='Control Panel'!$B$3)*('Sales Log'!$A$3:$A$2002<='Control Panel'!$C$3)*('Sales Log'!$H$3:$H$2002)) -> #VALUE! | E25: =C25-D25 -> #VALUE! | F25: =IF(C25>0,E25/C25*100,0) -> #VALUE!
A26: CM | B26: =SUMPRODUCT(('Sales Log'!$B$3:$B$2002="Mobile Shop")*('Sales Log'!$C$3:$C$2002="CM")*('Sales Log'!$A$3:$A$2002>='Control Panel'!$B$3)*('Sales Log'!$A$3:$A$2002<='Control Panel'!$C$3)*('Sales Log'!$D$3:$D$2002)) -> 0 | C26: =SUMPRODUCT(('Sales Log'!$B$3:$B$2002="Mobile Shop")*('Sales Log'!$C$3:$C$2002="CM")*('Sales Log'!$A$3:$A$2002>='Control Panel'!$B$3)*('Sales Log'!$A$3:$A$2002<='Control Panel'!$C$3)*('Sales Log'!$G$3:$G$2002)) -> #VALUE! | D26: =SUMPRODUCT(('Sales Log'!$B$3:$B$2002="Mobile Shop")*('Sales Log'!$C$3:$C$2002="CM")*('Sales Log'!$A$3:$A$2002>='Control Panel'!$B$3)*('Sales Log'!$A$3:$A$2002<='Control Panel'!$C$3)*('Sales Log'!$H$3:$H$2002)) -> #VALUE! | E26: =C26-D26 -> #VALUE! | F26: =IF(C26>0,E26/C26*100,0) -> #VALUE!
A27: BS | B27: =SUMPRODUCT(('Sales Log'!$B$3:$B$2002="Mobile Shop")*('Sales Log'!$C$3:$C$2002="BS")*('Sales Log'!$A$3:$A$2002>='Control Panel'!$B$3)*('Sales Log'!$A$3:$A$2002<='Control Panel'!$C$3)*('Sales Log'!$D$3:$D$2002)) -> 0 | C27: =SUMPRODUCT(('Sales Log'!$B$3:$B$2002="Mobile Shop")*('Sales Log'!$C$3:$C$2002="BS")*('Sales Log'!$A$3:$A$2002>='Control Panel'!$B$3)*('Sales Log'!$A$3:$A$2002<='Control Panel'!$C$3)*('Sales Log'!$G$3:$G$2002)) -> #VALUE! | D27: =SUMPRODUCT(('Sales Log'!$B$3:$B$2002="Mobile Shop")*('Sales Log'!$C$3:$C$2002="BS")*('Sales Log'!$A$3:$A$2002>='Control Panel'!$B$3)*('Sales Log'!$A$3:$A$2002<='Control Panel'!$C$3)*('Sales Log'!$H$3:$H$2002)) -> #VALUE! | E27: =C27-D27 -> #VALUE! | F27: =IF(C27>0,E27/C27*100,0) -> #VALUE!
A28: Hend 5% | B28: =SUMPRODUCT(('Sales Log'!$B$3:$B$2002="Mobile Shop")*('Sales Log'!$C$3:$C$2002="Hend 5%")*('Sales Log'!$A$3:$A$2002>='Control Panel'!$B$3)*('Sales Log'!$A$3:$A$2002<='Control Panel'!$C$3)*('Sales Log'!$D$3:$D$2002)) -> 10 | C28: =SUMPRODUCT(('Sales Log'!$B$3:$B$2002="Mobile Shop")*('Sales Log'!$C$3:$C$2002="Hend 5%")*('Sales Log'!$A$3:$A$2002>='Control Panel'!$B$3)*('Sales Log'!$A$3:$A$2002<='Control Panel'!$C$3)*('Sales Log'!$G$3:$G$2002)) -> #VALUE! | D28: =SUMPRODUCT(('Sales Log'!$B$3:$B$2002="Mobile Shop")*('Sales Log'!$C$3:$C$2002="Hend 5%")*('Sales Log'!$A$3:$A$2002>='Control Panel'!$B$3)*('Sales Log'!$A$3:$A$2002<='Control Panel'!$C$3)*('Sales Log'!$H$3:$H$2002)) -> #VALUE! | E28: =C28-D28 -> #VALUE! | F28: =IF(C28>0,E28/C28*100,0) -> #VALUE!
A29: GMG | B29: =SUMPRODUCT(('Sales Log'!$B$3:$B$2002="Mobile Shop")*('Sales Log'!$C$3:$C$2002="GMG")*('Sales Log'!$A$3:$A$2002>='Control Panel'!$B$3)*('Sales Log'!$A$3:$A$2002<='Control Panel'!$C$3)*('Sales Log'!$D$3:$D$2002)) -> 0 | C29: =SUMPRODUCT(('Sales Log'!$B$3:$B$2002="Mobile Shop")*('Sales Log'!$C$3:$C$2002="GMG")*('Sales Log'!$A$3:$A$2002>='Control Panel'!$B$3)*('Sales Log'!$A$3:$A$2002<='Control Panel'!$C$3)*('Sales Log'!$G$3:$G$2002)) -> #VALUE! | D29: =SUMPRODUCT(('Sales Log'!$B$3:$B$2002="Mobile Shop")*('Sales Log'!$C$3:$C$2002="GMG")*('Sales Log'!$A$3:$A$2002>='Control Panel'!$B$3)*('Sales Log'!$A$3:$A$2002<='Control Panel'!$C$3)*('Sales Log'!$H$3:$H$2002)) -> #VALUE! | E29: =C29-D29 -> #VALUE! | F29: =IF(C29>0,E29/C29*100,0) -> #VALUE!
A30: Crates | B30: =SUMPRODUCT(('Sales Log'!$B$3:$B$2002="Mobile Shop")*('Sales Log'!$C$3:$C$2002="Crates")*('Sales Log'!$A$3:$A$2002>='Control Panel'!$B$3)*('Sales Log'!$A$3:$A$2002<='Control Panel'!$C$3)*('Sales Log'!$D$3:$D$2002)) -> 0 | C30: =SUMPRODUCT(('Sales Log'!$B$3:$B$2002="Mobile Shop")*('Sales Log'!$C$3:$C$2002="Crates")*('Sales Log'!$A$3:$A$2002>='Control Panel'!$B$3)*('Sales Log'!$A$3:$A$2002<='Control Panel'!$C$3)*('Sales Log'!$G$3:$G$2002)) -> #VALUE! | D30: =SUMPRODUCT(('Sales Log'!$B$3:$B$2002="Mobile Shop")*('Sales Log'!$C$3:$C$2002="Crates")*('Sales Log'!$A$3:$A$2002>='Control Panel'!$B$3)*('Sales Log'!$A$3:$A$2002<='Control Panel'!$C$3)*('Sales Log'!$H$3:$H$2002)) -> #VALUE! | E30: =C30-D30 -> #VALUE! | F30: =IF(C30>0,E30/C30*100,0) -> #VALUE!
A32: Egg Shop
A33: Product | B33: Qty Sold | C33: Total Sales (GHS) | D33: Total Cost (GHS) | E33: Gross Profit (GHS) | F33: Margin %
A34: Extra Large | B34: =SUMPRODUCT(('Sales Log'!$B$3:$B$2002="Egg Shop")*('Sales Log'!$C$3:$C$2002="Extra Large")*('Sales Log'!$A$3:$A$2002>='Control Panel'!$B$3)*('Sales Log'!$A$3:$A$2002<='Control Panel'!$C$3)*('Sales Log'!$D$3:$D$2002)) -> 2 | C34: =SUMPRODUCT(('Sales Log'!$B$3:$B$2002="Egg Shop")*('Sales Log'!$C$3:$C$2002="Extra Large")*('Sales Log'!$A$3:$A$2002>='Control Panel'!$B$3)*('Sales Log'!$A$3:$A$2002<='Control Panel'!$C$3)*('Sales Log'!$G$3:$G$2002)) -> #VALUE! | D34: =SUMPRODUCT(('Sales Log'!$B$3:$B$2002="Egg Shop")*('Sales Log'!$C$3:$C$2002="Extra Large")*('Sales Log'!$A$3:$A$2002>='Control Panel'!$B$3)*('Sales Log'!$A$3:$A$2002<='Control Panel'!$C$3)*('Sales Log'!$H$3:$H$2002)) -> #VALUE! | E34: =C34-D34 -> #VALUE! | F34: =IF(C34>0,E34/C34*100,0) -> #VALUE!
A35: Large | B35: =SUMPRODUCT(('Sales Log'!$B$3:$B$2002="Egg Shop")*('Sales Log'!$C$3:$C$2002="Large")*('Sales Log'!$A$3:$A$2002>='Control Panel'!$B$3)*('Sales Log'!$A$3:$A$2002<='Control Panel'!$C$3)*('Sales Log'!$D$3:$D$2002)) -> 79 | C35: =SUMPRODUCT(('Sales Log'!$B$3:$B$2002="Egg Shop")*('Sales Log'!$C$3:$C$2002="Large")*('Sales Log'!$A$3:$A$2002>='Control Panel'!$B$3)*('Sales Log'!$A$3:$A$2002<='Control Panel'!$C$3)*('Sales Log'!$G$3:$G$2002)) -> #VALUE! | D35: =SUMPRODUCT(('Sales Log'!$B$3:$B$2002="Egg Shop")*('Sales Log'!$C$3:$C$2002="Large")*('Sales Log'!$A$3:$A$2002>='Control Panel'!$B$3)*('Sales Log'!$A$3:$A$2002<='Control Panel'!$C$3)*('Sales Log'!$H$3:$H$2002)) -> #VALUE! | E35: =C35-D35 -> #VALUE! | F35: =IF(C35>0,E35/C35*100,0) -> #VALUE!
A36: Medium | B36: =SUMPRODUCT(('Sales Log'!$B$3:$B$2002="Egg Shop")*('Sales Log'!$C$3:$C$2002="Medium")*('Sales Log'!$A$3:$A$2002>='Control Panel'!$B$3)*('Sales Log'!$A$3:$A$2002<='Control Panel'!$C$3)*('Sales Log'!$D$3:$D$2002)) -> 401 | C36: =SUMPRODUCT(('Sales Log'!$B$3:$B$2002="Egg Shop")*('Sales Log'!$C$3:$C$2002="Medium")*('Sales Log'!$A$3:$A$2002>='Control Panel'!$B$3)*('Sales Log'!$A$3:$A$2002<='Control Panel'!$C$3)*('Sales Log'!$G$3:$G$2002)) -> #VALUE! | D36: =SUMPRODUCT(('Sales Log'!$B$3:$B$2002="Egg Shop")*('Sales Log'!$C$3:$C$2002="Medium")*('Sales Log'!$A$3:$A$2002>='Control Panel'!$B$3)*('Sales Log'!$A$3:$A$2002<='Control Panel'!$C$3)*('Sales Log'!$H$3:$H$2002)) -> #VALUE! | E36: =C36-D36 -> #VALUE! | F36: =IF(C36>0,E36/C36*100,0) -> #VALUE!
A37: Small | B37: =SUMPRODUCT(('Sales Log'!$B$3:$B$2002="Egg Shop")*('Sales Log'!$C$3:$C$2002="Small")*('Sales Log'!$A$3:$A$2002>='Control Panel'!$B$3)*('Sales Log'!$A$3:$A$2002<='Control Panel'!$C$3)*('Sales Log'!$D$3:$D$2002)) -> 930.5 | C37: =SUMPRODUCT(('Sales Log'!$B$3:$B$2002="Egg Shop")*('Sales Log'!$C$3:$C$2002="Small")*('Sales Log'!$A$3:$A$2002>='Control Panel'!$B$3)*('Sales Log'!$A$3:$A$2002<='Control Panel'!$C$3)*('Sales Log'!$G$3:$G$2002)) -> #VALUE! | D37: =SUMPRODUCT(('Sales Log'!$B$3:$B$2002="Egg Shop")*('Sales Log'!$C$3:$C$2002="Small")*('Sales Log'!$A$3:$A$2002>='Control Panel'!$B$3)*('Sales Log'!$A$3:$A$2002<='Control Panel'!$C$3)*('Sales Log'!$H$3:$H$2002)) -> #VALUE! | E37: =C37-D37 -> #VALUE! | F37: =IF(C37>0,E37/C37*100,0) -> #VALUE!
A38: Pullet 1 | B38: =SUMPRODUCT(('Sales Log'!$B$3:$B$2002="Egg Shop")*('Sales Log'!$C$3:$C$2002="Pullet 1")*('Sales Log'!$A$3:$A$2002>='Control Panel'!$B$3)*('Sales Log'!$A$3:$A$2002<='Control Panel'!$C$3)*('Sales Log'!$D$3:$D$2002)) -> 1099 | C38: =SUMPRODUCT(('Sales Log'!$B$3:$B$2002="Egg Shop")*('Sales Log'!$C$3:$C$2002="Pullet 1")*('Sales Log'!$A$3:$A$2002>='Control Panel'!$B$3)*('Sales Log'!$A$3:$A$2002<='Control Panel'!$C$3)*('Sales Log'!$G$3:$G$2002)) -> #VALUE! | D38: =SUMPRODUCT(('Sales Log'!$B$3:$B$2002="Egg Shop")*('Sales Log'!$C$3:$C$2002="Pullet 1")*('Sales Log'!$A$3:$A$2002>='Control Panel'!$B$3)*('Sales Log'!$A$3:$A$2002<='Control Panel'!$C$3)*('Sales Log'!$H$3:$H$2002)) -> #VALUE! | E38: =C38-D38 -> #VALUE! | F38: =IF(C38>0,E38/C38*100,0) -> #VALUE!
A39: Pullet 2 | B39: =SUMPRODUCT(('Sales Log'!$B$3:$B$2002="Egg Shop")*('Sales Log'!$C$3:$C$2002="Pullet 2")*('Sales Log'!$A$3:$A$2002>='Control Panel'!$B$3)*('Sales Log'!$A$3:$A$2002<='Control Panel'!$C$3)*('Sales Log'!$D$3:$D$2002)) -> 251 | C39: =SUMPRODUCT(('Sales Log'!$B$3:$B$2002="Egg Shop")*('Sales Log'!$C$3:$C$2002="Pullet 2")*('Sales Log'!$A$3:$A$2002>='Control Panel'!$B$3)*('Sales Log'!$A$3:$A$2002<='Control Panel'!$C$3)*('Sales Log'!$G$3:$G$2002)) -> #VALUE! | D39: =SUMPRODUCT(('Sales Log'!$B$3:$B$2002="Egg Shop")*('Sales Log'!$C$3:$C$2002="Pullet 2")*('Sales Log'!$A$3:$A$2002>='Control Panel'!$B$3)*('Sales Log'!$A$3:$A$2002<='Control Panel'!$C$3)*('Sales Log'!$H$3:$H$2002)) -> #VALUE! | E39: =C39-D39 -> #VALUE! | F39: =IF(C39>0,E39/C39*100,0) -> #VALUE!
A40: Broken | B40: =SUMPRODUCT(('Sales Log'!$B$3:$B$2002="Egg Shop")*('Sales Log'!$C$3:$C$2002="Broken")*('Sales Log'!$A$3:$A$2002>='Control Panel'!$B$3)*('Sales Log'!$A$3:$A$2002<='Control Panel'!$C$3)*('Sales Log'!$D$3:$D$2002)) -> 16.5 | C40: =SUMPRODUCT(('Sales Log'!$B$3:$B$2002="Egg Shop")*('Sales Log'!$C$3:$C$2002="Broken")*('Sales Log'!$A$3:$A$2002>='Control Panel'!$B$3)*('Sales Log'!$A$3:$A$2002<='Control Panel'!$C$3)*('Sales Log'!$G$3:$G$2002)) -> #VALUE! | D40: =SUMPRODUCT(('Sales Log'!$B$3:$B$2002="Egg Shop")*('Sales Log'!$C$3:$C$2002="Broken")*('Sales Log'!$A$3:$A$2002>='Control Panel'!$B$3)*('Sales Log'!$A$3:$A$2002<='Control Panel'!$C$3)*('Sales Log'!$H$3:$H$2002)) -> #VALUE! | E40: =C40-D40 -> #VALUE! | F40: =IF(C40>0,E40/C40*100,0) -> #VALUE!

Sheet Loans
A1: LOAN REGISTER
A2: Enter each loan below. Monthly Payment = Principal + Interest combined repayment.
A4: Loan # | B4: Lender / Description | C4: Start Date | D4: Original Amount (GHS) | E4: Interest Rate (% p.a.) | F4: Term (Months) | G4: Monthly Payment (GHS) | H4: Outstanding Balance (GHS)
A5: 1
A6: 2
A7: 3
A8: 4
A9: 5
A10: 6
A11: 7
A12: 8
A13: 9
A14: 10
A16: SUMMARY
A17: Total Monthly Repayments (GHS) | H17: =SUMIF(G5:G14,">0",G5:G14) -> 0
A18: Total Outstanding Balance (GHS) | H18: =SUMIF(H5:H14,">0",H5:H14) -> 0
A19: Number of Active Loans | H19: =COUNTIF(H5:H14,">0") -> 0
A21: HOW TO USE: • Fill in Lender, Start Date, Original Amount, Interest Rate, Term and Monthly Payment for each loan. • Update 'Outstanding Balance' each month after making a repayment. • The Balance Sheet 'Loans Payable' pulls from Total Outstanding Balance (H19). • Record each monthly repayment in Shop Expenses with category 'Loan Repayment'.

Sheet Income Statement
A1: INCOME STATEMENT
A2: Period: | B2: =TEXT('Control Panel'!$B$3,"DD-MMM-YYYY")&" to "&TEXT('Control Panel'!$C$3,"DD-MMM-YYYY") -> 01-Apr-2026 to 31-May-2026
A4: REVENUE (All Cash Sales)
A5: Trading Shops Sales | C5: =SUMIFS('Sales Log'!$G$3:$G$2002,'Sales Log'!$B$3:$B$2002,"<>Egg Shop",'Sales Log'!$A$3:$A$2002,">="&'Control Panel'!$B$3,'Sales Log'!$A$3:$A$2002,"<="&'Control Panel'!$C$3) -> 225961
A6: Egg Shop Sales | C6: =SUMIFS('Sales Log'!$G$3:$G$2002,'Sales Log'!$B$3:$B$2002,"Egg Shop",'Sales Log'!$A$3:$A$2002,">="&'Control Panel'!$B$3,'Sales Log'!$A$3:$A$2002,"<="&'Control Panel'!$C$3) -> 131080.5
A7: TOTAL REVENUE | C7: =C5+C6 -> 357041.5
A9: COST OF SALES
A10: Cost of Goods Sold | C10: =SUMIFS('Sales Log'!$H$3:$H$2002,'Sales Log'!$A$3:$A$2002,">="&'Control Panel'!$B$3,'Sales Log'!$A$3:$A$2002,"<="&'Control Panel'!$C$3) -> 350133.5
A11: Farm Production Costs | C11: =SUMIFS('Farm Costs'!$D$3:$D$2002,'Farm Costs'!$A$3:$A$2002,">="&'Control Panel'!$B$3,'Farm Costs'!$A$3:$A$2002,"<="&'Control Panel'!$C$3) -> 27215
A12: TOTAL COST OF SALES | C12: =C10+C11 -> 377348.5
A14: GROSS PROFIT | C14: =C7-C12 -> -20307
A16: OPERATING EXPENSES
A17: Shop Rent | C17: =SUMIFS('Shop Expenses'!$D$3:$D$2002,'Shop Expenses'!$C$3:$C$2002,"Rent",'Shop Expenses'!$A$3:$A$2002,">="&'Control Panel'!$B$3,'Shop Expenses'!$A$3:$A$2002,"<="&'Control Panel'!$C$3) -> 640
A18: Shop Salaries | C18: =SUMIFS('Shop Expenses'!$D$3:$D$2002,'Shop Expenses'!$C$3:$C$2002,"Salary",'Shop Expenses'!$A$3:$A$2002,">="&'Control Panel'!$B$3,'Shop Expenses'!$A$3:$A$2002,"<="&'Control Panel'!$C$3) -> 3100
A19: Other Expenses | C19: =SUMIFS('Shop Expenses'!$D$3:$D$2002,'Shop Expenses'!$C$3:$C$2002,"<>Rent",'Shop Expenses'!$A$3:$A$2002,">="&'Control Panel'!$B$3,'Shop Expenses'!$A$3:$A$2002,"<="&'Control Panel'!$C$3)-SUMIFS('Shop Expenses'!$D$3:$D$2002,'Shop Expenses'!$C$3:$C$2002,"Salary",'Shop Expenses'!$A$3:$A$2002,">="&'Control Panel'!$B$3,'Shop Expenses'!$A$3:$A$2002,"<="&'Control Panel'!$C$3)-SUMIFS('Shop Expenses'!$D$3:$D$2002,'Shop Expenses'!$C$3:$C$2002,"Loan Repayment",'Shop Expenses'!$A$3:$A$2002,">="&'Control Panel'!$B$3,'Shop Expenses'!$A$3:$A$2002,"<="&'Control Panel'!$C$3) -> 0
A20: Loan Repayments | C20: =SUMIFS('Shop Expenses'!$D$3:$D$2002,'Shop Expenses'!$C$3:$C$2002,"Loan Repayment",'Shop Expenses'!$A$3:$A$2002,">="&'Control Panel'!$B$3,'Shop Expenses'!$A$3:$A$2002,"<="&'Control Panel'!$C$3) -> 0
A21: TOTAL EXPENSES | C21: =C17+C18+C19+C20 -> 3740
A23: NET PROFIT / (LOSS) | C23: =C14-C21 -> -24047

Sheet Balance Sheet
A1: BALANCE SHEET
A2: As at: | B2: =TEXT('Control Panel'!$C$3,"DD-MMM-YYYY") -> 31-May-2026
A4: ASSETS
A5: Current Assets
A6: Cash at Bank | C6: ='Control Panel'!B7+SUMIFS('Sales Log'!$G$3:$G$2002,'Sales Log'!$A$3:$A$2002,">="&'Control Panel'!$B$3,'Sales Log'!$A$3:$A$2002,"<="&'Control Panel'!$C$3)-SUMIFS('Shop Expenses'!$D$3:$D$2002,'Shop Expenses'!$A$3:$A$2002,">="&'Control Panel'!$B$3,'Shop Expenses'!$A$3:$A$2002,"<="&'Control Panel'!$C$3)-SUMIFS('Farm Costs'!$D$3:$D$2002,'Farm Costs'!$A$3:$A$2002,">="&'Control Panel'!$B$3,'Farm Costs'!$A$3:$A$2002,"<="&'Control Panel'!$C$3) -> 327086.5
A7: Trading Stock (at cost) | C7: =SUMIFS(Purchases!$G$3:$G$2002,Purchases!$A$3:$A$2002,">="&'Control Panel'!$B$3,Purchases!$A$3:$A$2002,"<="&'Control Panel'!$C$3)-SUMIFS('Sales Log'!$H$3:$H$2002,'Sales Log'!$B$3:$B$2002,"<>Egg Shop",'Sales Log'!$A$3:$A$2002,">="&'Control Panel'!$B$3,'Sales Log'!$A$3:$A$2002,"<="&'Control Panel'!$C$3) -> 74847
A8: Feed Ingredients Stock | C8: ='Feed Inventory'!H8 -> 0
A9: TOTAL CURRENT ASSETS | C9: =SUM(C6:C8) -> 401933.5
A11: LIABILITIES
A12: Accounts Payable | C12: =0 -> 0
A13: Accrued Expenses | C13: =0 -> 0
A14: Loans Payable | C14: =IF(ISREF(Loans!H19),Loans!H19,0) -> 0
A15: TOTAL LIABILITIES | C15: =C12+C13+C14 -> 0
A17: EQUITY
A18: Owner's Equity (Opening Capital) | C18: ='Control Panel'!B7 -> 1000
A19: Net Profit for Period | C19: =SUMIFS('Sales Log'!$G$3:$G$2002,'Sales Log'!$A$3:$A$2002,">="&'Control Panel'!$B$3,'Sales Log'!$A$3:$A$2002,"<="&'Control Panel'!$C$3)-SUMIFS('Sales Log'!$H$3:$H$2002,'Sales Log'!$A$3:$A$2002,">="&'Control Panel'!$B$3,'Sales Log'!$A$3:$A$2002,"<="&'Control Panel'!$C$3)-SUMIFS('Shop Expenses'!$D$3:$D$2002,'Shop Expenses'!$A$3:$A$2002,">="&'Control Panel'!$B$3,'Shop Expenses'!$A$3:$A$2002,"<="&'Control Panel'!$C$3)-SUMIFS('Farm Costs'!$D$3:$D$2002,'Farm Costs'!$A$3:$A$2002,">="&'Control Panel'!$B$3,'Farm Costs'!$A$3:$A$2002,"<="&'Control Panel'!$C$3) -> -24047
A20: TOTAL EQUITY | C20: =C18+C19 -> -23047
A22: BALANCE CHECK
A23: Total Assets | C23: =C9 -> 401933.5
A24: Total Liabilities + Equity | C24: =C15+C20 -> -23047
A25: Difference (should be 0) | C25: =C23-C24 -> 424980.5

Sheet Daily Shop Sales
A1: DAILY SALES BY SHOP
A2: Date | B2: Akatsi Feed | C2: Abor Feed | D2: Mobile Shop | E2: Egg Shop | F2: Total Sales (GHS)
B3: =IF(OR($A3="",B$2=""),"",SUMIFS('Sales Log'!$G$3:$G$2002,'Sales Log'!$A$3:$A$2002,$A3,'Sales Log'!$B$3:$B$2002,B$2)) | C3: =IF(OR($A3="",C$2=""),"",SUMIFS('Sales Log'!$G$3:$G$2002,'Sales Log'!$A$3:$A$2002,$A3,'Sales Log'!$B$3:$B$2002,C$2)) | D3: =IF(OR($A3="",D$2=""),"",SUMIFS('Sales Log'!$G$3:$G$2002,'Sales Log'!$A$3:$A$2002,$A3,'Sales Log'!$B$3:$B$2002,D$2)) | E3: =IF(OR($A3="",E$2=""),"",SUMIFS('Sales Log'!$G$3:$G$2002,'Sales Log'!$A$3:$A$2002,$A3,'Sales Log'!$B$3:$B$2002,E$2)) | F3: =IF(A3="","",SUM(B3:E3))
B4: =IF(OR($A4="",B$2=""),"",SUMIFS('Sales Log'!$G$3:$G$2002,'Sales Log'!$A$3:$A$2002,$A4,'Sales Log'!$B$3:$B$2002,B$2)) | C4: =IF(OR($A4="",C$2=""),"",SUMIFS('Sales Log'!$G$3:$G$2002,'Sales Log'!$A$3:$A$2002,$A4,'Sales Log'!$B$3:$B$2002,C$2)) | D4: =IF(OR($A4="",D$2=""),"",SUMIFS('Sales Log'!$G$3:$G$2002,'Sales Log'!$A$3:$A$2002,$A4,'Sales Log'!$B$3:$B$2002,D$2)) | E4: =IF(OR($A4="",E$2=""),"",SUMIFS('Sales Log'!$G$3:$G$2002,'Sales Log'!$A$3:$A$2002,$A4,'Sales Log'!$B$3:$B$2002,E$2)) | F4: =IF(A4="","",SUM(B4:E4))
B5: =IF(OR($A5="",B$2=""),"",SUMIFS('Sales Log'!$G$3:$G$2002,'Sales Log'!$A$3:$A$2002,$A5,'Sales Log'!$B$3:$B$2002,B$2)) | C5: =IF(OR($A5="",C$2=""),"",SUMIFS('Sales Log'!$G$3:$G$2002,'Sales Log'!$A$3:$A$2002,$A5,'Sales Log'!$B$3:$B$2002,C$2)) | D5: =IF(OR($A5="",D$2=""),"",SUMIFS('Sales Log'!$G$3:$G$2002,'Sales Log'!$A$3:$A$2002,$A5,'Sales Log'!$B$3:$B$2002,D$2)) | E5: =IF(OR($A5="",E$2=""),"",SUMIFS('Sales Log'!$G$3:$G$2002,'Sales Log'!$A$3:$A$2002,$A5,'Sales Log'!$B$3:$B$2002,E$2)) | F5: =IF(A5="","",SUM(B5:E5))
B6: =IF(OR($A6="",B$2=""),"",SUMIFS('Sales Log'!$G$3:$G$2002,'Sales Log'!$A$3:$A$2002,$A6,'Sales Log'!$B$3:$B$2002,B$2)) | C6: =IF(OR($A6="",C$2=""),"",SUMIFS('Sales Log'!$G$3:$G$2002,'Sales Log'!$A$3:$A$2002,$A6,'Sales Log'!$B$3:$B$2002,C$2)) | D6: =IF(OR($A6="",D$2=""),"",SUMIFS('Sales Log'!$G$3:$G$2002,'Sales Log'!$A$3:$A$2002,$A6,'Sales Log'!$B$3:$B$2002,D$2)) | E6: =IF(OR($A6="",E$2=""),"",SUMIFS('Sales Log'!$G$3:$G$2002,'Sales Log'!$A$3:$A$2002,$A6,'Sales Log'!$B$3:$B$2002,E$2)) | F6: =IF(A6="","",SUM(B6:E6))
B7: =IF(OR($A7="",B$2=""),"",SUMIFS('Sales Log'!$G$3:$G$2002,'Sales Log'!$A$3:$A$2002,$A7,'Sales Log'!$B$3:$B$2002,B$2)) | C7: =IF(OR($A7="",C$2=""),"",SUMIFS('Sales Log'!$G$3:$G$2002,'Sales Log'!$A$3:$A$2002,$A7,'Sales Log'!$B$3:$B$2002,C$2)) | D7: =IF(OR($A7="",D$2=""),"",SUMIFS('Sales Log'!$G$3:$G$2002,'Sales Log'!$A$3:$A$2002,$A7,'Sales Log'!$B$3:$B$2002,D$2)) | E7: =IF(OR($A7="",E$2=""),"",SUMIFS('Sales Log'!$G$3:$G$2002,'Sales Log'!$A$3:$A$2002,$A7,'Sales Log'!$B$3:$B$2002,E$2)) | F7: =IF(A7="","",SUM(B7:E7))
B8: =IF(OR($A8="",B$2=""),"",SUMIFS('Sales Log'!$G$3:$G$2002,'Sales Log'!$A$3:$A$2002,$A8,'Sales Log'!$B$3:$B$2002,B$2)) | C8: =IF(OR($A8="",C$2=""),"",SUMIFS('Sales Log'!$G$3:$G$2002,'Sales Log'!$A$3:$A$2002,$A8,'Sales Log'!$B$3:$B$2002,C$2)) | D8: =IF(OR($A8="",D$2=""),"",SUMIFS('Sales Log'!$G$3:$G$2002,'Sales Log'!$A$3:$A$2002,$A8,'Sales Log'!$B$3:$B$2002,D$2)) | E8: =IF(OR($A8="",E$2=""),"",SUMIFS('Sales Log'!$G$3:$G$2002,'Sales Log'!$A$3:$A$2002,$A8,'Sales Log'!$B$3:$B$2002,E$2)) | F8: =IF(A8="","",SUM(B8:E8))
B9: =IF(OR($A9="",B$2=""),"",SUMIFS('Sales Log'!$G$3:$G$2002,'Sales Log'!$A$3:$A$2002,$A9,'Sales Log'!$B$3:$B$2002,B$2)) | C9: =IF(OR($A9="",C$2=""),"",SUMIFS('Sales Log'!$G$3:$G$2002,'Sales Log'!$A$3:$A$2002,$A9,'Sales Log'!$B$3:$B$2002,C$2)) | D9: =IF(OR($A9="",D$2=""),"",SUMIFS('Sales Log'!$G$3:$G$2002,'Sales Log'!$A$3:$A$2002,$A9,'Sales Log'!$B$3:$B$2002,D$2)) | E9: =IF(OR($A9="",E$2=""),"",SUMIFS('Sales Log'!$G$3:$G$2002,'Sales Log'!$A$3:$A$2002,$A9,'Sales Log'!$B$3:$B$2002,E$2)) | F9: =IF(A9="","",SUM(B9:E9))
B10: =IF(OR($A10="",B$2=""),"",SUMIFS('Sales Log'!$G$3:$G$2002,'Sales Log'!$A$3:$A$2002,$A10,'Sales Log'!$B$3:$B$2002,B$2)) | C10: =IF(OR($A10="",C$2=""),"",SUMIFS('Sales Log'!$G$3:$G$2002,'Sales Log'!$A$3:$A$2002,$A10,'Sales Log'!$B$3:$B$2002,C$2)) | D10: =IF(OR($A10="",D$2=""),"",SUMIFS('Sales Log'!$G$3:$G$2002,'Sales Log'!$A$3:$A$2002,$A10,'Sales Log'!$B$3:$B$2002,D$2)) | E10: =IF(OR($A10="",E$2=""),"",SUMIFS('Sales Log'!$G$3:$G$2002,'Sales Log'!$A$3:$A$2002,$A10,'Sales Log'!$B$3:$B$2002,E$2)) | F10: =IF(A10="","",SUM(B10:E10))
B11: =IF(OR($A11="",B$2=""),"",SUMIFS('Sales Log'!$G$3:$G$2002,'Sales Log'!$A$3:$A$2002,$A11,'Sales Log'!$B$3:$B$2002,B$2)) | C11: =IF(OR($A11="",C$2=""),"",SUMIFS('Sales Log'!$G$3:$G$2002,'Sales Log'!$A$3:$A$2002,$A11,'Sales Log'!$B$3:$B$2002,C$2)) | D11: =IF(OR($A11="",D$2=""),"",SUMIFS('Sales Log'!$G$3:$G$2002,'Sales Log'!$A$3:$A$2002,$A11,'Sales Log'!$B$3:$B$2002,D$2)) | E11: =IF(OR($A11="",E$2=""),"",SUMIFS('Sales Log'!$G$3:$G$2002,'Sales Log'!$A$3:$A$2002,$A11,'Sales Log'!$B$3:$B$2002,E$2)) | F11: =IF(A11="","",SUM(B11:E11))
B12: =IF(OR($A12="",B$2=""),"",SUMIFS('Sales Log'!$G$3:$G$2002,'Sales Log'!$A$3:$A$2002,$A12,'Sales Log'!$B$3:$B$2002,B$2)) | C12: =IF(OR($A12="",C$2=""),"",SUMIFS('Sales Log'!$G$3:$G$2002,'Sales Log'!$A$3:$A$2002,$A12,'Sales Log'!$B$3:$B$2002,C$2)) | D12: =IF(OR($A12="",D$2=""),"",SUMIFS('Sales Log'!$G$3:$G$2002,'Sales Log'!$A$3:$A$2002,$A12,'Sales Log'!$B$3:$B$2002,D$2)) | E12: =IF(OR($A12="",E$2=""),"",SUMIFS('Sales Log'!$G$3:$G$2002,'Sales Log'!$A$3:$A$2002,$A12,'Sales Log'!$B$3:$B$2002,E$2)) | F12: =IF(A12="","",SUM(B12:E12))
B13: =IF(OR($A13="",B$2=""),"",SUMIFS('Sales Log'!$G$3:$G$2002,'Sales Log'!$A$3:$A$2002,$A13,'Sales Log'!$B$3:$B$2002,B$2)) | C13: =IF(OR($A13="",C$2=""),"",SUMIFS('Sales Log'!$G$3:$G$2002,'Sales Log'!$A$3:$A$2002,$A13,'Sales Log'!$B$3:$B$2002,C$2)) | D13: =IF(OR($A13="",D$2=""),"",SUMIFS('Sales Log'!$G$3:$G$2002,'Sales Log'!$A$3:$A$2002,$A13,'Sales Log'!$B$3:$B$2002,D$2)) | E13: =IF(OR($A13="",E$2=""),"",SUMIFS('Sales Log'!$G$3:$G$2002,'Sales Log'!$A$3:$A$2002,$A13,'Sales Log'!$B$3:$B$2002,E$2)) | F13: =IF(A13="","",SUM(B13:E13))
B14: =IF(OR($A14="",B$2=""),"",SUMIFS('Sales Log'!$G$3:$G$2002,'Sales Log'!$A$3:$A$2002,$A14,'Sales Log'!$B$3:$B$2002,B$2)) | C14: =IF(OR($A14="",C$2=""),"",SUMIFS('Sales Log'!$G$3:$G$2002,'Sales Log'!$A$3:$A$2002,$A14,'Sales Log'!$B$3:$B$2002,C$2)) | D14: =IF(OR($A14="",D$2=""),"",SUMIFS('Sales Log'!$G$3:$G$2002,'Sales Log'!$A$3:$A$2002,$A14,'Sales Log'!$B$3:$B$2002,D$2)) | E14: =IF(OR($A14="",E$2=""),"",SUMIFS('Sales Log'!$G$3:$G$2002,'Sales Log'!$A$3:$A$2002,$A14,'Sales Log'!$B$3:$B$2002,E$2)) | F14: =IF(A14="","",SUM(B14:E14))
... B367: =IF(OR($A367="",B$2=""),"",SUMIFS('Sales Log'!$G$3:$G$2002,'Sales Log'!$A$3:$A$2002,$A367,'Sales Log'!$B$3:$B$2002,B$2)) | C367: =IF(OR($A367="",C$2=""),"",SUMIFS('Sales Log'!$G$3:$G$2002,'Sales Log'!$A$3:$A$2002,$A367,'Sales Log'!$B$3:$B$2002,C$2)) | D367: =IF(OR($A367="",D$2=""),"",SUMIFS('Sales Log'!$G$3:$G$2002,'Sales Log'!$A$3:$A$2002,$A367,'Sales Log'!$B$3:$B$2002,D$2)) | E367: =IF(OR($A367="",E$2=""),"",SUMIFS('Sales Log'!$G$3:$G$2002,'Sales Log'!$A$3:$A$2002,$A367,'Sales Log'!$B$3:$B$2002,E$2)) | F367: =IF(A367="","",SUM(B367:E367))

Sheet Daily Valuation
A1: DAILY BUSINESS VALUATION
A2: Valuation Date | C2: 46137
A4: CASH & BANK | D4: Value (GHS)
A5: Cash in Hand | D5: 0
A6: Bank Balance | D6: 0
A7: TRADING STOCK (at cost) | D7: Value (GHS)
A8: Akatsi Feed - LM | D8: 0
A9: Akatsi Feed - GM | D9: 0
A10: Akatsi Feed - CM | D10: 0
A11: Akatsi Feed - Crates | D11: 0
A12: Abor Feed - LM | D12: 0
A13: Abor Feed - GM | D13: 0
A14: Mobile Shop - LM | D14: 0
A15: Mobile Shop - GM | D15: 0
A16: EGG STOCK (at farm cost) | D16: Value (GHS)
A17: Extra Large eggs | D17: 0
A18: Large eggs | D18: 0
A19: Medium eggs | D19: 0
A20: Small eggs | D20: 0
A21: Pullet 1 eggs | D21: 0
A22: Pullet 2 eggs | D22: 0
A23: FEED INGREDIENTS | D23: Value (GHS)
A24: Total Feed Stock Value (auto) | D24: ='Feed Inventory'!H8 -> 0
A26: TOTAL BUSINESS VALUE (GHS) | D26: =SUM(D5:D24) -> 0

Sheet Growth Tracker
A1: BUSINESS GROWTH TRACKER
A2: Month | B2: Total Sales | C2: Total Costs | D2: Gross Profit | E2: Total Expenses | F2: Net Profit | G2: Business Value | H2: MoM Sales Change | I2: MoM Profit Change | J2: Sales Growth % | K2: Status
A3: Apr 2026 | B3: 116613.5 | C3: 99443 | D3: =B3-C3 -> 17170.5 | E3: 3640 | F3: =D3-E3 -> 13530.5 | G3: 0 | H3: — | I3: — | J3: — | K3: =IF(F3>0,"GROWING",IF(F3=0,"FLAT","DECLINING")) -> GROWING
A4: May 2026 | B4: 0 | C4: 0 | D4: =B4-C4 -> 0 | E4: 0 | F4: =D4-E4 -> 0 | G4: 0 | K4: =IF(F4>0,"GROWING",IF(F4=0,"FLAT","DECLINING")) -> FLAT
A5: Jun 2026 | B5: 0 | C5: 0 | D5: =B5-C5 -> 0 | E5: 0 | F5: =D5-E5 -> 0 | G5: 0 | K5: =IF(F5>0,"GROWING",IF(F5=0,"FLAT","DECLINING")) -> FLAT
A6: Jul 2026 | B6: 0 | C6: 0 | D6: =B6-C6 -> 0 | E6: 0 | F6: =D6-E6 -> 0 | G6: 0 | K6: =IF(F6>0,"GROWING",IF(F6=0,"FLAT","DECLINING")) -> FLAT
A7: Aug 2026 | B7: 0 | C7: 0 | D7: =B7-C7 -> 0 | E7: 0 | F7: =D7-E7 -> 0 | G7: 0 | K7: =IF(F7>0,"GROWING",IF(F7=0,"FLAT","DECLINING")) -> FLAT
A8: Sep 2026 | B8: 0 | C8: 0 | D8: =B8-C8 -> 0 | E8: 0 | F8: =D8-E8 -> 0 | G8: 0 | K8: =IF(F8>0,"GROWING",IF(F8=0,"FLAT","DECLINING")) -> FLAT
A9: Oct 2026 | B9: 0 | C9: 0 | D9: =B9-C9 -> 0 | E9: 0 | F9: =D9-E9 -> 0 | G9: 0 | K9: =IF(F9>0,"GROWING",IF(F9=0,"FLAT","DECLINING")) -> FLAT
A10: Nov 2026 | B10: 0 | C10: 0 | D10: =B10-C10 -> 0 | E10: 0 | F10: =D10-E10 -> 0 | G10: 0 | K10: =IF(F10>0,"GROWING",IF(F10=0,"FLAT","DECLINING")) -> FLAT
A11: Dec 2026 | B11: 0 | C11: 0 | D11: =B11-C11 -> 0 | E11: 0 | F11: =D11-E11 -> 0 | G11: 0 | K11: =IF(F11>0,"GROWING",IF(F11=0,"FLAT","DECLINING")) -> FLAT
A12: Jan 2027 | B12: 0 | C12: 0 | D12: =B12-C12 -> 0 | E12: 0 | F12: =D12-E12 -> 0 | G12: 0 | K12: =IF(F12>0,"GROWING",IF(F12=0,"FLAT","DECLINING")) -> FLAT
A13: Feb 2027 | B13: 0 | C13: 0 | D13: =B13-C13 -> 0 | E13: 0 | F13: =D13-E13 -> 0 | G13: 0 | K13: =IF(F13>0,"GROWING",IF(F13=0,"FLAT","DECLINING")) -> FLAT
A14: Mar 2027 | B14: 0 | C14: 0 | D14: =B14-C14 -> 0 | E14: 0 | F14: =D14-E14 -> 0 | G14: 0 | K14: =IF(F14>0,"GROWING",IF(F14=0,"FLAT","DECLINING")) -> FLAT
A15: ANNUAL TOTAL / AVG | D15: =B15-C15 -> 0 | F15: =D15-E15 -> 0 | K15: =IF(F15>0,"GROWING",IF(F15=0,"FLAT","DECLINING")) -> FLAT
A16: BUSINESS SCORECARD (Latest Month) | D16: =B16-C16 -> 0 | F16: =D16-E16 -> 0 | K16: =IF(F16>0,"GROWING",IF(F16=0,"FLAT","DECLINING")) -> FLAT
A17: Best Month (Sales) | D17: =B17-C17 -> 0 | F17: =D17-E17 -> 0 | K17: =IF(F17>0,"GROWING",IF(F17=0,"FLAT","DECLINING")) -> FLAT
A18: Best Month (Profit) | D18: =B18-C18 -> 0 | F18: =D18-E18 -> 0 | K18: =IF(F18>0,"GROWING",IF(F18=0,"FLAT","DECLINING")) -> FLAT
A19: Worst Month (Profit) | D19: =B19-C19 -> 0 | F19: =D19-E19 -> 0 | K19: =IF(F19>0,"GROWING",IF(F19=0,"FLAT","DECLINING")) -> FLAT
A20: Avg Monthly Sales | D20: =B20-C20 -> 0 | F20: =D20-E20 -> 0 | K20: =IF(F20>0,"GROWING",IF(F20=0,"FLAT","DECLINING")) -> FLAT
A21: Avg Monthly Profit | D21: =B21-C21 -> 0 | F21: =D21-E21 -> 0 | K21: =IF(F21>0,"GROWING",IF(F21=0,"FLAT","DECLINING")) -> FLAT
A22: Avg Profit Margin % | D22: =B22-C22 -> 0 | F22: =D22-E22 -> 0 | K22: =IF(F22>0,"GROWING",IF(F22=0,"FLAT","DECLINING")) -> FLAT
A23: Overall Trend | D23: =B23-C23 -> 0 | F23: =D23-E23 -> 0 | K23: =IF(F23>0,"GROWING",IF(F23=0,"FLAT","DECLINING")) -> FLAT

Sheet Read Me
A1: GMGL ACCOUNTS – USER GUIDE
A2: SYSTEM RULES
A3: 1. NO CREDIT SALES | B3: All sales must be cash. Payment column is always Cash.
A4: 2. CASH AUTO-BANKED | B4: Every sale in Sales Log auto-appears in Cash & Bank Money In.
A5: 3. CONTROL PANEL | B5: Set Start/End Date (row 3) and Opening Bank Balance (row 7).
A6: 4. COST PRICE AUTO | B6: Sales Log col F auto-looks up Unit Cost from Purchases col F via Key match.
A7: 5. PROTECTED SHEETS | B7: Report sheets are locked. Password: gmgl2026
A9: SHEET GUIDE
A10: Control Panel | B10: Set report dates and opening bank balance here first.
A11: Setup | B11: Reference lists for shops, products, farm cost items.
A12: Chart of Accounts | B12: Full account code list.
A13: Purchases | B13: Record all stock purchases. Supplier column is yellow (fill in).
A14: Sales Log | B14: Record all cash sales. Cost price auto-fills from Purchases.
A15: Farm Costs | B15: Record all farm production costs with category.
A16: Egg Transfers | B16: Record eggs sent from farm to Egg Shop.
A17: Shop Expenses | B17: Record shop-level expenses (Rent, Salary, etc.).
A18: Payroll | B18: Staff register and monthly wage summary.
A19: Cash & Bank | B19: Enter dates in col A. Money In and Out auto-fill.
A20: Stock Summary | B20: Received vs Sold vs Remaining for the report period.
A21: Feed Inventory | B21: Manual entry of feed ingredient quantities and values.
... A28: Growth Tracker | B28: Month-by-month performance history.
